Workbook

Sheet ´Master
A1: key | B1: model | C1: project | D1: question | E1: AA_v1 | F1: NA_v1 | G1: LLM1_v1 | H1: LLM2_v1 | I1: AA_v2 | J1: NA_v2 | K1: LLM1_v2 | L1: LLM2_v2 | M1: AA_v3 | N1: NA_v3 | O1: LLM1_v3 | P1: LLM2_v3 | Q1: AA_v4 | R1: NA_v4 | S1: LLM1_v4 | T1: LLM2_v4 | U1: AA_v5 | V1: NA_v5 | W1: LLM1_v5 | X1: LLM2_v5
A2: qwen3_US285851_Q28 | B2: =VLOOKUP(A2,'v1'!A:B,2,FALSE) -> qwen3 | C2: =VLOOKUP(A2,'v1'!A:C,3,FALSE) -> US285851 | D2: =VLOOKUP(RIGHT(A2,3),Questions!A:C,3,FALSE) -> 4 | E2: =VLOOKUP(A2,'v1'!A:G,7,FALSE) -> 1 | F2: =VLOOKUP(A2,'v1'!A:H,8,FALSE) -> 1 | G2: =VLOOKUP(A2,'GPT4-judge1'!A:G,6,FALSE) -> 3 | H2: =VLOOKUP(A2,GP5_judge1!A:F,6,FALSE) -> 3 | I2: =VLOOKUP(A2,'v2'!A:H,7,FALSE) -> 3 | J2: =VLOOKUP(A2,'v2'!A:H,8,FALSE) -> 1 | K2: =VLOOKUP(A2,GP4_judge2!A:F,6,FALSE) -> 3 | L2: =VLOOKUP(A2,GP5_judge2!A:F,6,FALSE) -> 3 | M2: =VLOOKUP(A2,'v3'!A:H,7,FALSE) -> 2 | N2: =VLOOKUP(A2,'v3'!A:H,8,FALSE) -> 2 | O2: =VLOOKUP(A2,GP4_judge3!A:F,6,FALSE) -> 3 | P2: =VLOOKUP(A2,GP5_judge3!A:F,6,FALSE) -> 3 | Q2: =VLOOKUP(A2,'v4'!A:H,7,FALSE) -> 3 | R2: =VLOOKUP(A2,'v4'!A:H,8,FALSE) -> 3 | S2: =VLOOKUP(A2,GP4_judge4!A:F,6,FALSE) -> 3 | T2: =VLOOKUP(A2,'GP5-judge4'!A:F,6,FALSE) -> 3 | U2: =VLOOKUP(A2,'v5'!A:H,7,FALSE) -> 0 | V2: =VLOOKUP(A2,'v5'!A:H,8,FALSE) -> 3 | W2: =VLOOKUP(A2,GP4_judge5!A:F,6,FALSE) -> 3 | X2: =VLOOKUP(A2,GP5_judge5!A:F,6,FALSE) -> 3
A3: qwen3_US285851_Q29 | B3: =VLOOKUP(A3,'v1'!A:B,2,FALSE) -> qwen3 | C3: =VLOOKUP(A3,'v1'!A:C,3,FALSE) -> US285851 | D3: =VLOOKUP(RIGHT(A3,3),Questions!A:C,3,FALSE) -> 5 | E3: =VLOOKUP(A3,'v1'!A:G,7,FALSE) -> 1 | F3: =VLOOKUP(A3,'v1'!A:H,8,FALSE) -> 1 | G3: =VLOOKUP(A3,'GPT4-judge1'!A:G,6,FALSE) -> 3 | H3: =VLOOKUP(A3,GP5_judge1!A:F,6,FALSE) -> 3 | I3: =VLOOKUP(A3,'v2'!A:H,7,FALSE) -> 3 | J3: =VLOOKUP(A3,'v2'!A:H,8,FALSE) -> 1 | K3: =VLOOKUP(A3,GP4_judge2!A:F,6,FALSE) -> 3 | L3: =VLOOKUP(A3,GP5_judge2!A:F,6,FALSE) -> 3 | M3: =VLOOKUP(A3,'v3'!A:H,7,FALSE) -> 0 | N3: =VLOOKUP(A3,'v3'!A:H,8,FALSE) -> 1 | O3: =VLOOKUP(A3,GP4_judge3!A:F,6,FALSE) -> 3 | P3: =VLOOKUP(A3,GP5_judge3!A:F,6,FALSE) -> 3 | Q3: =VLOOKUP(A3,'v4'!A:H,7,FALSE) -> 2 | R3: =VLOOKUP(A3,'v4'!A:H,8,FALSE) -> 1 | S3: =VLOOKUP(A3,GP4_judge4!A:F,6,FALSE) -> 3 | T3: =VLOOKUP(A3,'GP5-judge4'!A:F,6,FALSE) -> 3 | U3: =VLOOKUP(A3,'v5'!A:H,7,FALSE) -> 1 | V3: =VLOOKUP(A3,'v5'!A:H,8,FALSE) -> 0 | W3: =VLOOKUP(A3,GP4_judge5!A:F,6,FALSE) -> 3 | X3: =VLOOKUP(A3,GP5_judge5!A:F,6,FALSE) -> 3
A4: qwen3_US285851_Q30 | B4: =VLOOKUP(A4,'v1'!A:B,2,FALSE) -> qwen3 | C4: =VLOOKUP(A4,'v1'!A:C,3,FALSE) -> US285851 | D4: =VLOOKUP(RIGHT(A4,3),Questions!A:C,3,FALSE) -> 2 | E4: =VLOOKUP(A4,'v1'!A:G,7,FALSE) -> 0 | F4: =VLOOKUP(A4,'v1'!A:H,8,FALSE) -> 1 | G4: =VLOOKUP(A4,'GPT4-judge1'!A:G,6,FALSE) -> 3 | H4: =VLOOKUP(A4,GP5_judge1!A:F,6,FALSE) -> 2 | I4: =VLOOKUP(A4,'v2'!A:H,7,FALSE) -> 0 | J4: =VLOOKUP(A4,'v2'!A:H,8,FALSE) -> 1 | K4: =VLOOKUP(A4,GP4_judge2!A:F,6,FALSE) -> 3 | L4: =VLOOKUP(A4,GP5_judge2!A:F,6,FALSE) -> 2 | M4: =VLOOKUP(A4,'v3'!A:H,7,FALSE) -> 0 | N4: =VLOOKUP(A4,'v3'!A:H,8,FALSE) -> 0 | O4: =VLOOKUP(A4,GP4_judge3!A:F,6,FALSE) -> 3 | P4: =VLOOKUP(A4,GP5_judge3!A:F,6,FALSE) -> 2 | Q4: =VLOOKUP(A4,'v4'!A:H,7,FALSE) -> 0 | R4: =VLOOKUP(A4,'v4'!A:H,8,FALSE) -> 0 | S4: =VLOOKUP(A4,GP4_judge4!A:F,6,FALSE) -> 3 | T4: =VLOOKUP(A4,'GP5-judge4'!A:F,6,FALSE) -> 2 | U4: =VLOOKUP(A4,'v5'!A:H,7,FALSE) -> 0 | V4: =VLOOKUP(A4,'v5'!A:H,8,FALSE) -> 1 | W4: =VLOOKUP(A4,GP4_judge5!A:F,6,FALSE) -> 3 | X4: =VLOOKUP(A4,GP5_judge5!A:F,6,FALSE) -> 2
A5: qwen3_US285851_Q31 | B5: =VLOOKUP(A5,'v1'!A:B,2,FALSE) -> qwen3 | C5: =VLOOKUP(A5,'v1'!A:C,3,FALSE) -> US285851 | D5: =VLOOKUP(RIGHT(A5,3),Questions!A:C,3,FALSE) -> 6 | E5: =VLOOKUP(A5,'v1'!A:G,7,FALSE) -> 0 | F5: =VLOOKUP(A5,'v1'!A:H,8,FALSE) -> 1 | G5: =VLOOKUP(A5,'GPT4-judge1'!A:G,6,FALSE) -> 3 | H5: =VLOOKUP(A5,GP5_judge1!A:F,6,FALSE) -> 3 | I5: =VLOOKUP(A5,'v2'!A:H,7,FALSE) -> 1 | J5: =VLOOKUP(A5,'v2'!A:H,8,FALSE) -> 1 | K5: =VLOOKUP(A5,GP4_judge2!A:F,6,FALSE) -> 3 | L5: =VLOOKUP(A5,GP5_judge2!A:F,6,FALSE) -> 3 | M5: =VLOOKUP(A5,'v3'!A:H,7,FALSE) -> 1 | N5: =VLOOKUP(A5,'v3'!A:H,8,FALSE) -> 1 | O5: =VLOOKUP(A5,GP4_judge3!A:F,6,FALSE) -> 3 | P5: =VLOOKUP(A5,GP5_judge3!A:F,6,FALSE) -> 3 | Q5: =VLOOKUP(A5,'v4'!A:H,7,FALSE) -> 0 | R5: =VLOOKUP(A5,'v4'!A:H,8,FALSE) -> 1 | S5: =VLOOKUP(A5,GP4_judge4!A:F,6,FALSE) -> 3 | T5: =VLOOKUP(A5,'GP5-judge4'!A:F,6,FALSE) -> 3 | U5: =VLOOKUP(A5,'v5'!A:H,7,FALSE) -> 1 | V5: =VLOOKUP(A5,'v5'!A:H,8,FALSE) -> 0 | W5: =VLOOKUP(A5,GP4_judge5!A:F,6,FALSE) -> 3 | X5: =VLOOKUP(A5,GP5_judge5!A:F,6,FALSE) -> 3
A6: qwen3_US285851_Q32 | B6: =VLOOKUP(A6,'v1'!A:B,2,FALSE) -> qwen3 | C6: =VLOOKUP(A6,'v1'!A:C,3,FALSE) -> US285851 | D6: =VLOOKUP(RIGHT(A6,3),Questions!A:C,3,FALSE) -> 1 | E6: =VLOOKUP(A6,'v1'!A:G,7,FALSE) -> 0 | F6: =VLOOKUP(A6,'v1'!A:H,8,FALSE) -> 0 | G6: =VLOOKUP(A6,'GPT4-judge1'!A:G,6,FALSE) -> 3 | H6: =VLOOKUP(A6,GP5_judge1!A:F,6,FALSE) -> 3 | I6: =VLOOKUP(A6,'v2'!A:H,7,FALSE) -> 0 | J6: =VLOOKUP(A6,'v2'!A:H,8,FALSE) -> 0 | K6: =VLOOKUP(A6,GP4_judge2!A:F,6,FALSE) -> 3 | L6: =VLOOKUP(A6,GP5_judge2!A:F,6,FALSE) -> 3 | M6: =VLOOKUP(A6,'v3'!A:H,7,FALSE) -> 0 | N6: =VLOOKUP(A6,'v3'!A:H,8,FALSE) -> 0 | O6: =VLOOKUP(A6,GP4_judge3!A:F,6,FALSE) -> 3 | P6: =VLOOKUP(A6,GP5_judge3!A:F,6,FALSE) -> 3 | Q6: =VLOOKUP(A6,'v4'!A:H,7,FALSE) -> 0 | R6: =VLOOKUP(A6,'v4'!A:H,8,FALSE) -> 0 | S6: =VLOOKUP(A6,GP4_judge4!A:F,6,FALSE) -> 3 | T6: =VLOOKUP(A6,'GP5-judge4'!A:F,6,FALSE) -> 3 | U6: =VLOOKUP(A6,'v5'!A:H,7,FALSE) -> 1 | V6: =VLOOKUP(A6,'v5'!A:H,8,FALSE) -> 2 | W6: =VLOOKUP(A6,GP4_judge5!A:F,6,FALSE) -> 3 | X6: =VLOOKUP(A6,GP5_judge5!A:F,6,FALSE) -> 3
A7: qwen3_US285851_Q33 | B7: =VLOOKUP(A7,'v1'!A:B,2,FALSE) -> qwen3 | C7: =VLOOKUP(A7,'v1'!A:C,3,FALSE) -> US285851 | D7: =VLOOKUP(RIGHT(A7,3),Questions!A:C,3,FALSE) -> 8 | E7: =VLOOKUP(A7,'v1'!A:G,7,FALSE) -> 1 | F7: =VLOOKUP(A7,'v1'!A:H,8,FALSE) -> 1 | G7: =VLOOKUP(A7,'GPT4-judge1'!A:G,6,FALSE) -> 3 | H7: =VLOOKUP(A7,GP5_judge1!A:F,6,FALSE) -> 3 | I7: =VLOOKUP(A7,'v2'!A:H,7,FALSE) -> 2 | J7: =VLOOKUP(A7,'v2'!A:H,8,FALSE) -> 1 | K7: =VLOOKUP(A7,GP4_judge2!A:F,6,FALSE) -> 3 | L7: =VLOOKUP(A7,GP5_judge2!A:F,6,FALSE) -> 3 | M7: =VLOOKUP(A7,'v3'!A:H,7,FALSE) -> 1 | N7: =VLOOKUP(A7,'v3'!A:H,8,FALSE) -> 1 | O7: =VLOOKUP(A7,GP4_judge3!A:F,6,FALSE) -> 3 | P7: =VLOOKUP(A7,GP5_judge3!A:F,6,FALSE) -> 3 | Q7: =VLOOKUP(A7,'v4'!A:H,7,FALSE) -> 2 | R7: =VLOOKUP(A7,'v4'!A:H,8,FALSE) -> 2 | S7: =VLOOKUP(A7,GP4_judge4!A:F,6,FALSE) -> 3 | T7: =VLOOKUP(A7,'GP5-judge4'!A:F,6,FALSE) -> 3 | U7: =VLOOKUP(A7,'v5'!A:H,7,FALSE) -> 2 | V7: =VLOOKUP(A7,'v5'!A:H,8,FALSE) -> 2 | W7: =VLOOKUP(A7,GP4_judge5!A:F,6,FALSE) -> 3 | X7: =VLOOKUP(A7,GP5_judge5!A:F,6,FALSE) -> 3
A8: qwen3_US285851_Q34 | B8: =VLOOKUP(A8,'v1'!A:B,2,FALSE) -> qwen3 | C8: =VLOOKUP(A8,'v1'!A:C,3,FALSE) -> US285851 | D8: =VLOOKUP(RIGHT(A8,3),Questions!A:C,3,FALSE) -> 3 | E8: =VLOOKUP(A8,'v1'!A:G,7,FALSE) -> 1 | F8: =VLOOKUP(A8,'v1'!A:H,8,FALSE) -> 1 | G8: =VLOOKUP(A8,'GPT4-judge1'!A:G,6,FALSE) -> 3 | H8: =VLOOKUP(A8,GP5_judge1!A:F,6,FALSE) -> 3 | I8: =VLOOKUP(A8,'v2'!A:H,7,FALSE) -> 2 | J8: =VLOOKUP(A8,'v2'!A:H,8,FALSE) -> 2 | K8: =VLOOKUP(A8,GP4_judge2!A:F,6,FALSE) -> 3 | L8: =VLOOKUP(A8,GP5_judge2!A:F,6,FALSE) -> 3 | M8: =VLOOKUP(A8,'v3'!A:H,7,FALSE) -> 0 | N8: =VLOOKUP(A8,'v3'!A:H,8,FALSE) -> 0 | O8: =VLOOKUP(A8,GP4_judge3!A:F,6,FALSE) -> 3 | P8: =VLOOKUP(A8,GP5_judge3!A:F,6,FALSE) -> 3 | Q8: =VLOOKUP(A8,'v4'!A:H,7,FALSE) -> 0 | R8: =VLOOKUP(A8,'v4'!A:H,8,FALSE) -> 0 | S8: =VLOOKUP(A8,GP4_judge4!A:F,6,FALSE) -> 3 | T8: =VLOOKUP(A8,'GP5-judge4'!A:F,6,FALSE) -> 3 | U8: =VLOOKUP(A8,'v5'!A:H,7,FALSE) -> 0 | V8: =VLOOKUP(A8,'v5'!A:H,8,FALSE) -> 0 | W8: =VLOOKUP(A8,GP4_judge5!A:F,6,FALSE) -> 3 | X8: =VLOOKUP(A8,GP5_judge5!A:F,6,FALSE) -> 3
A9: qwen3_US285851_Q35 | B9: =VLOOKUP(A9,'v1'!A:B,2,FALSE) -> qwen3 | C9: =VLOOKUP(A9,'v1'!A:C,3,FALSE) -> US285851 | D9: =VLOOKUP(RIGHT(A9,3),Questions!A:C,3,FALSE) -> 10 | E9: =VLOOKUP(A9,'v1'!A:G,7,FALSE) -> 2 | F9: =VLOOKUP(A9,'v1'!A:H,8,FALSE) -> 2 | G9: =VLOOKUP(A9,'GPT4-judge1'!A:G,6,FALSE) -> 3 | H9: =VLOOKUP(A9,GP5_judge1!A:F,6,FALSE) -> 3 | I9: =VLOOKUP(A9,'v2'!A:H,7,FALSE) -> 1 | J9: =VLOOKUP(A9,'v2'!A:H,8,FALSE) -> 1 | K9: =VLOOKUP(A9,GP4_judge2!A:F,6,FALSE) -> 3 | L9: =VLOOKUP(A9,GP5_judge2!A:F,6,FALSE) -> 3 | M9: =VLOOKUP(A9,'v3'!A:H,7,FALSE) -> 2 | N9: =VLOOKUP(A9,'v3'!A:H,8,FALSE) -> 1 | O9: =VLOOKUP(A9,GP4_judge3!A:F,6,FALSE) -> 3 | P9: =VLOOKUP(A9,GP5_judge3!A:F,6,FALSE) -> 3 | Q9: =VLOOKUP(A9,'v4'!A:H,7,FALSE) -> 2 | R9: =VLOOKUP(A9,'v4'!A:H,8,FALSE) -> 2 | S9: =VLOOKUP(A9,GP4_judge4!A:F,6,FALSE) -> 3 | T9: =VLOOKUP(A9,'GP5-judge4'!A:F,6,FALSE) -> 3 | U9: =VLOOKUP(A9,'v5'!A:H,7,FALSE) -> 2 | V9: =VLOOKUP(A9,'v5'!A:H,8,FALSE) -> 3 | W9: =VLOOKUP(A9,GP4_judge5!A:F,6,FALSE) -> 3 | X9: =VLOOKUP(A9,GP5_judge5!A:F,6,FALSE) -> 3
A10: qwen3_US285851_Q36 | B10: =VLOOKUP(A10,'v1'!A:B,2,FALSE) -> qwen3 | C10: =VLOOKUP(A10,'v1'!A:C,3,FALSE) -> US285851 | D10: =VLOOKUP(RIGHT(A10,3),Questions!A:C,3,FALSE) -> 9 | E10: =VLOOKUP(A10,'v1'!A:G,7,FALSE) -> 1 | F10: =VLOOKUP(A10,'v1'!A:H,8,FALSE) -> 1 | G10: =VLOOKUP(A10,'GPT4-judge1'!A:G,6,FALSE) -> 3 | H10: =VLOOKUP(A10,GP5_judge1!A:F,6,FALSE) -> 3 | I10: =VLOOKUP(A10,'v2'!A:H,7,FALSE) -> 1 | J10: =VLOOKUP(A10,'v2'!A:H,8,FALSE) -> 1 | K10: =VLOOKUP(A10,GP4_judge2!A:F,6,FALSE) -> 3 | L10: =VLOOKUP(A10,GP5_judge2!A:F,6,FALSE) -> 3 | M10: =VLOOKUP(A10,'v3'!A:H,7,FALSE) -> 2 | N10: =VLOOKUP(A10,'v3'!A:H,8,FALSE) -> 1 | O10: =VLOOKUP(A10,GP4_judge3!A:F,6,FALSE) -> 3 | P10: =VLOOKUP(A10,GP5_judge3!A:F,6,FALSE) -> 3 | Q10: =VLOOKUP(A10,'v4'!A:H,7,FALSE) -> 1 | R10: =VLOOKUP(A10,'v4'!A:H,8,FALSE) -> 2 | S10: =VLOOKUP(A10,GP4_judge4!A:F,6,FALSE) -> 3 | T10: =VLOOKUP(A10,'GP5-judge4'!A:F,6,FALSE) -> 3 | U10: =VLOOKUP(A10,'v5'!A:H,7,FALSE) -> 2 | V10: =VLOOKUP(A10,'v5'!A:H,8,FALSE) -> 2 | W10: =VLOOKUP(A10,GP4_judge5!A:F,6,FALSE) -> 3 | X10: =VLOOKUP(A10,GP5_judge5!A:F,6,FALSE) -> 3
A11: qwen3_US285851_Q37 | B11: =VLOOKUP(A11,'v1'!A:B,2,FALSE) -> qwen3 | C11: =VLOOKUP(A11,'v1'!A:C,3,FALSE) -> US285851 | D11: =VLOOKUP(RIGHT(A11,3),Questions!A:C,3,FALSE) -> 7 | E11: =VLOOKUP(A11,'v1'!A:G,7,FALSE) -> 2 | F11: =VLOOKUP(A11,'v1'!A:H,8,FALSE) -> 1 | G11: =VLOOKUP(A11,'GPT4-judge1'!A:G,6,FALSE) -> 3 | H11: =VLOOKUP(A11,GP5_judge1!A:F,6,FALSE) -> 3 | I11: =VLOOKUP(A11,'v2'!A:H,7,FALSE) -> 3 | J11: =VLOOKUP(A11,'v2'!A:H,8,FALSE) -> 1 | K11: =VLOOKUP(A11,GP4_judge2!A:F,6,FALSE) -> 3 | L11: =VLOOKUP(A11,GP5_judge2!A:F,6,FALSE) -> 3 | M11: =VLOOKUP(A11,'v3'!A:H,7,FALSE) -> 2 | N11: =VLOOKUP(A11,'v3'!A:H,8,FALSE) -> 1 | O11: =VLOOKUP(A11,GP4_judge3!A:F,6,FALSE) -> 3 | P11: =VLOOKUP(A11,GP5_judge3!A:F,6,FALSE) -> 3 | Q11: =VLOOKUP(A11,'v4'!A:H,7,FALSE) -> 2 | R11: =VLOOKUP(A11,'v4'!A:H,8,FALSE) -> 2 | S11: =VLOOKUP(A11,GP4_judge4!A:F,6,FALSE) -> 3 | T11: =VLOOKUP(A11,'GP5-judge4'!A:F,6,FALSE) -> 3 | U11: =VLOOKUP(A11,'v5'!A:H,7,FALSE) -> 2 | V11: =VLOOKUP(A11,'v5'!A:H,8,FALSE) -> 3 | W11: =VLOOKUP(A11,GP4_judge5!A:F,6,FALSE) -> 3 | X11: =VLOOKUP(A11,GP5_judge5!A:F,6,FALSE) -> 3
A12: qwen3_US293949_Q38 | B12: =VLOOKUP(A12,'v1'!A:B,2,FALSE) -> qwen3 | C12: =VLOOKUP(A12,'v1'!A:C,3,FALSE) -> US293949 | D12: =VLOOKUP(RIGHT(A12,3),Questions!A:C,3,FALSE) -> 4 | E12: =VLOOKUP(A12,'v1'!A:G,7,FALSE) -> 2 | F12: =VLOOKUP(A12,'v1'!A:H,8,FALSE) -> 1 | G12: =VLOOKUP(A12,'GPT4-judge1'!A:G,6,FALSE) -> 3 | H12: =VLOOKUP(A12,GP5_judge1!A:F,6,FALSE) -> 3 | I12: =VLOOKUP(A12,'v2'!A:H,7,FALSE) -> 2 | J12: =VLOOKUP(A12,'v2'!A:H,8,FALSE) -> 1 | K12: =VLOOKUP(A12,GP4_judge2!A:F,6,FALSE) -> 3 | L12: =VLOOKUP(A12,GP5_judge2!A:F,6,FALSE) -> 3 | M12: =VLOOKUP(A12,'v3'!A:H,7,FALSE) -> 0 | N12: =VLOOKUP(A12,'v3'!A:H,8,FALSE) -> 0 | O12: =VLOOKUP(A12,GP4_judge3!A:F,6,FALSE) -> 3 | P12: =VLOOKUP(A12,GP5_judge3!A:F,6,FALSE) -> 3 | Q12: =VLOOKUP(A12,'v4'!A:H,7,FALSE) -> 0 | R12: =VLOOKUP(A12,'v4'!A:H,8,FALSE) -> 0 | S12: =VLOOKUP(A12,GP4_judge4!A:F,6,FALSE) -> 3 | T12: =VLOOKUP(A12,'GP5-judge4'!A:F,6,FALSE) -> 2 | U12: =VLOOKUP(A12,'v5'!A:H,7,FALSE) -> 0 | V12: =VLOOKUP(A12,'v5'!A:H,8,FALSE) -> 2 | W12: =VLOOKUP(A12,GP4_judge5!A:F,6,FALSE) -> 2 | X12: =VLOOKUP(A12,GP5_judge5!A:F,6,FALSE) -> 3
A13: qwen3_US293949_Q39 | B13: =VLOOKUP(A13,'v1'!A:B,2,FALSE) -> qwen3 | C13: =VLOOKUP(A13,'v1'!A:C,3,FALSE) -> US293949 | D13: =VLOOKUP(RIGHT(A13,3),Questions!A:C,3,FALSE) -> 5 | E13: =VLOOKUP(A13,'v1'!A:G,7,FALSE) -> 0 | F13: =VLOOKUP(A13,'v1'!A:H,8,FALSE) -> 0 | G13: =VLOOKUP(A13,'GPT4-judge1'!A:G,6,FALSE) -> 3 | H13: =VLOOKUP(A13,GP5_judge1!A:F,6,FALSE) -> 3 | I13: =VLOOKUP(A13,'v2'!A:H,7,FALSE) -> 0 | J13: =VLOOKUP(A13,'v2'!A:H,8,FALSE) -> 1 | K13: =VLOOKUP(A13,GP4_judge2!A:F,6,FALSE) -> 3 | L13: =VLOOKUP(A13,GP5_judge2!A:F,6,FALSE) -> 3 | M13: =VLOOKUP(A13,'v3'!A:H,7,FALSE) -> 0 | N13: =VLOOKUP(A13,'v3'!A:H,8,FALSE) -> 1 | O13: =VLOOKUP(A13,GP4_judge3!A:F,6,FALSE) -> 3 | P13: =VLOOKUP(A13,GP5_judge3!A:F,6,FALSE) -> 3 | Q13: =VLOOKUP(A13,'v4'!A:H,7,FALSE) -> 2 | R13: =VLOOKUP(A13,'v4'!A:H,8,FALSE) -> 1 | S13: =VLOOKUP(A13,GP4_judge4!A:F,6,FALSE) -> 3 | T13: =VLOOKUP(A13,'GP5-judge4'!A:F,6,FALSE) -> 3 | U13: =VLOOKUP(A13,'v5'!A:H,7,FALSE) -> 1 | V13: =VLOOKUP(A13,'v5'!A:H,8,FALSE) -> 0 | W13: =VLOOKUP(A13,GP4_judge5!A:F,6,FALSE) -> 3 | X13: =VLOOKUP(A13,GP5_judge5!A:F,6,FALSE) -> 3
... A201: deepseek-r1_US285851_Q35 | B201: =VLOOKUP(A201,'v1'!A:B,2,FALSE) -> deepseek-r1 | C201: =VLOOKUP(A201,'v1'!A:C,3,FALSE) -> US285851 | D201: =VLOOKUP(RIGHT(A201,3),Questions!A:C,3,FALSE) -> 10 | E201: =VLOOKUP(A201,'v1'!A:G,7,FALSE) -> 1 | F201: =VLOOKUP(A201,'v1'!A:H,8,FALSE) -> 1 | G201: =VLOOKUP(A201,'GPT4-judge1'!A:G,6,FALSE) -> 3 | H201: =VLOOKUP(A201,GP5_judge1!A:F,6,FALSE) -> 3 | I201: =VLOOKUP(A201,'v2'!A:H,7,FALSE) -> 2 | J201: =VLOOKUP(A201,'v2'!A:H,8,FALSE) -> 3 | K201: =VLOOKUP(A201,GP4_judge2!A:F,6,FALSE) -> 2 | L201: =VLOOKUP(A201,GP5_judge2!A:F,6,FALSE) -> 3 | M201: =VLOOKUP(A201,'v3'!A:H,7,FALSE) -> #N/A | N201: =VLOOKUP(A201,'v3'!A:H,8,FALSE) -> #N/A | O201: =VLOOKUP(A201,GP4_judge3!A:F,6,FALSE) -> #N/A | P201: =VLOOKUP(A201,GP5_judge3!A:F,6,FALSE) -> #N/A | Q201: =VLOOKUP(A201,'v4'!A:H,7,FALSE) -> #N/A | R201: =VLOOKUP(A201,'v4'!A:H,8,FALSE) -> #N/A | S201: =VLOOKUP(A201,GP4_judge4!A:F,6,FALSE) -> #N/A | T201: =VLOOKUP(A201,'GP5-judge4'!A:F,6,FALSE) -> #N/A | U201: =VLOOKUP(A201,'v5'!A:H,7,FALSE) -> #N/A | V201: =VLOOKUP(A201,'v5'!A:H,8,FALSE) -> #N/A | W201: =VLOOKUP(A201,GP4_judge5!A:F,6,FALSE) -> #N/A | X201: =VLOOKUP(A201,GP5_judge5!A:F,6,FALSE) -> #N/A

Sheet GP5_judge1
A1: Master Key | B1: model | C1: projectID | D1: questionID | E1: answer | F1: Grade
A2: =_xlfn.CONCAT(C2,"_",D2) -> llama3.2_US285851_Q28 | B2: gpt-5-chat-latest | C2: llama3.2_US285851 | D2: Q28 | E2: **2** – The conclusion is logically structured and acknowledges the lack of budget and timing compliance data, leading to a reasonable, cautious answer (“uncertain whether completed on time and within budget”). It correctly identifies missing information as a limiting factor and gives a sensible recommendation. However, it does not explicitly reference any concrete evidence from the timeline (such as total project span or delays) to strengthen the assessment, which keeps it from the highest score. | F2: =RIGHT(LEFT(E2,3),1) -> 2
A3: =_xlfn.CONCAT(C3,"_",D3) -> llama3.2_US285851_Q29 | B3: gpt-5-chat-latest | C3: llama3.2_US285851 | D3: Q29 | E3: **2** **Explanation:** The answer shows some understanding of the project plan and correctly points out unusual entries (e.g., zeroday tasks) and potentially long activities that could cause delays. It also identifies possible structural issues like unclear milestones or dependencies. However, the analysis remains somewhat general and speculative — it doesn’t clearly identify where actual delays occurred or connect them directly to the project timeline. The causes presented (“lack of assignment,” “external dependencies”) are reasonable hypotheses but lack concrete evidence from the provided data. Overall, it demonstrates partial insight (above minimal comprehension) but falls short of a detailed, wellsupported explanation — thus merits a **2** on the 0–3 scale. | F3: =RIGHT(LEFT(E3,3),1) -> 2
A4: =_xlfn.CONCAT(C4,"_",D4) -> llama3.2_US285851_Q30 | B4: gpt-5-chat-latest | C4: llama3.2_US285851 | D4: Q30 | E4: **2** The final conclusions provide a generally sound, moderately detailed assessment. The answer clearly notes that there were deviations in timeline and resource allocation and acknowledges the lack of contextual data needed for a full evaluation. It shows reasonable understanding of the event log and logical reasoning about adherence to plan and objectives. However, it does not offer strong evidence directly connected to specific data points or timelines in the log (e.g., identifying the *Confirmar/garantir fonte orçamentária* 55day duration as a likely bottleneck) and remains somewhat generic. The reasoning is correct but not deeply datadriven or conclusive. Overall, the answer demonstrates fair analytical quality — better than superficial (so not a “1”), but short of a fully wellsubstantiated analysis (so not a “3”). | F4: =RIGHT(LEFT(E4,3),1) -> 2
A5: =_xlfn.CONCAT(C5,"_",D5) -> llama3.2_US285851_Q31 | B5: gpt-5-chat-latest | C5: llama3.2_US285851 | D5: Q31 | E5: **Grade: 2** **Explanation:** The final part of the answer reasonably addresses the question based on the available data. It correctly observes that the event log does not explicitly mention issues or obstacles, and it identifies potentially long-duration tasks as possible indicators of challenges. The response also suggests what additional information would be needed for a more complete assessment, showing understanding of project risk and issue management concepts. However, it lacks a direct evaluation or synthesis — for instance, it doesn’t explicitly state whether the long tasks reflect actual issues or normal project steps, nor does it propose conclusions about how issues were managed. The response remains somewhat generic and exploratory rather than conclusive, which makes it solid but not fully complete. | F5: 2
A6: =_xlfn.CONCAT(C6,"_",D6) -> llama3.2_US285851_Q32 | B6: gpt-5-chat-latest | C6: llama3.2_US285851 | D6: Q32 | E6: **2** The final conclusions of the answer are relevant and generally accurate — the respondent correctly notes that the provided project plan doesn’t include sufficient information to definitively assess whether the project stayed within allocated resources. The answer acknowledges gaps in data (human, financial, technical) and provides reasonable recommendations for further analysis. However, it stops short of offering a clear, direct conclusion (e.g., “No, we cannot determine resource adherence based on available data”) and is somewhat generic in its recommendations. Thus, it demonstrates good understanding but lacks precise closure and specific linkage to the given project log—earning a **2 out of 3**. | F6: =RIGHT(LEFT(E6,3),1) -> 2
A7: =_xlfn.CONCAT(C7,"_",D7) -> llama3.2_US285851_Q33 | B7: gpt-5-chat-latest | C7: llama3.2_US285851 | D7: Q33 | E7: **3** The final conclusions are well structured, relevant, and directly address systemic improvement areas in project execution. The answer identifies specific and actionable enhancements—scope clarity, risk management, sequencing, communication, and overlap reduction—which are all grounded in standard project management best practices. The reasoning is coherent and aligns with the issues observable in the provided event log (e.g., long idle periods, overlapping or redundant tasks). Overall, this is a strong, well-reasoned answer deserving the maximum grade. | F7: =RIGHT(LEFT(E7,3),1) -> 3
A8: =_xlfn.CONCAT(C8,"_",D8) -> llama3.2_US285851_Q34 | B8: gpt-5-chat-latest | C8: llama3.2_US285851 | D8: Q34 | E8: **2** The final conclusion is coherent and cautious: it acknowledges the available data and logically infers that milestones *seem* to have been met, given no explicit evidence of delay. However, it remains largely generic, reiterating the lack of milestone tracking data instead of offering a concrete or well-substantiated assessment based on the provided log. - **Strengths:** Reasonable logic; clear acknowledgment of data limitations; consistent reasoning. - **Weaknesses:** Too generic; lacks direct reference to key events or long-duration tasks as potential delays (e.g., “Confirmar/garantir fonte orçamentária” lasting 55 days); does not explicitly confirm or refute milestone achievement based on project end alignment. Overall, it shows understanding but not a thorough evaluation — deserving a **2/3**. | F8: =RIGHT(LEFT(E8,3),1) -> 2
A9: =_xlfn.CONCAT(C9,"_",D9) -> llama3.2_US285851_Q35 | B9: gpt-5-chat-latest | C9: llama3.2_US285851 | D9: Q35 | E9: **3** The final recommendations are coherent, actionable, and directly relevant to the issues visible in the project log (e.g., vague roles, lack of risk mitigation, unclear milestones). They demonstrate a good understanding of project management best practices, addressing structure, stakeholder engagement, and continuous monitoring. The answer is comprehensive and well-organized, making it a strong and complete response worthy of the maximum grade. | F9: =RIGHT(LEFT(E9,3),1) -> 3
A10: =_xlfn.CONCAT(C10,"_",D10) -> llama3.2_US285851_Q36 | B10: gpt-5-chat-latest | C10: llama3.2_US285851 | D10: Q36 | E10: **3** The final conclusions are clear, accurate, and well-grounded in the project plan. The response identifies both positive aspects (clear scope definition, monitoring, communication, and change control) and a key improvement point (risk of scope creep). It demonstrates understanding of scope management lessons learned and ties them to specific project events. The reasoning is coherent and appropriately balanced, showing full comprehension of project scope management principles. | F10: =RIGHT(LEFT(E10,3),1) -> 3
A11: =_xlfn.CONCAT(C11,"_",D11) -> llama3.2_US285851_Q37 | B11: gpt-5-chat-latest | C11: llama3.2_US285851 | D11: Q37 | E11: **3** The final conclusions are comprehensive, clearly structured, and highly relevant to the event log provided. The advice addresses multiple key project management dimensions — planning, communication, risk management, progress tracking, adaptability, quality assurance, and role clarity — all of which are directly applicable to future similar projects. The points are actionable and demonstrate a strong understanding of project execution challenges. Overall, this is a complete and well-justified response deserving the highest grade on the 0–3 scale. | F11: =RIGHT(LEFT(E11,3),1) -> 3
A12: =_xlfn.CONCAT(C12,"_",D12) -> llama3.2_US293949_Q38 | B12: gpt-5-chat-latest | C12: llama3.2_US293949 | D12: Q38 | E12: **2** **Reasoning:** The final conclusion correctly recognizes the limited information available (no explicit budget or baseline deadlines) and appropriately avoids making unsupported claims. It identifies relevant timeline concerns and examples from the log, showing reasonable analytical thinking. However, it remains somewhat generic and inconclusive—it doesn’t synthesize findings into a clear final judgment about timeliness or performance relative to expectations. The answer is accurate and cautious but lacks depth or decisive evaluation expected for a top score. | F12: =RIGHT(LEFT(E12,3),1) -> 2
A13: =_xlfn.CONCAT(C13,"_",D13) -> llama3.2_US293949_Q39 | B13: gpt-5-chat-latest | C13: llama3.2_US293949 | D13: Q39 | E13: **2** **Justification:** The final conclusions correctly observe that no explicit delays are described in the event log and provide plausible general causes for potential delays (resource constraints, insufficient time allocation, etc.). The answer also acknowledges task overlaps and dependencies that might suggest risk areas. However, the analysis is relatively generic: it doesn’t clearly point to concrete evidence of delays visible in the event data (for example, unusually long durations like the 30day postimplementation activity or extended “Certificação da Implantação” tasks). As a result, while logically coherent and relevant, it lacks precision and depth in connecting findings directly to the dataset. | F13: =RIGHT(LEFT(E13,3),1) -> 2
A14: =_xlfn.CONCAT(C14,"_",D14) -> llama3.2_US293949_Q40 | B14: gpt-5-chat-latest | C14: llama3.2_US293949 | D14: Q40 | E14: **2** The conclusion provides a coherent assessment based on the available evidence, identifying partial adherence to the original plan, mentioning delays and revisions, and recognizing progress where appropriate. However, it remains somewhat generic and lacks strong linkage to specific project objectives or a clear quantitative evaluation of adherence. It demonstrates a reasonable but not comprehensive understanding — solid reasoning but not fully thorough or precise — deserving a **2 (good but not excellent)** on a 0–3 scale. | F14: =RIGHT(LEFT(E14,3),1) -> 2
A15: =_xlfn.CONCAT(C15,"_",D15) -> llama3.2_US293949_Q41 | B15: gpt-5-chat-latest | C15: llama3.2_US293949 | D15: Q41 | E15: **2** **Explanation:** The final conclusions demonstrate a reasonable understanding of the project plan and identify potential areas that might indicate issues (especially the long-duration tasks). The answer correctly notes the lack of contextual data and avoids unfounded claims. However, it doesn’t clearly state that unexpected issues were observed — it only hypothesizes what could indicate them. The discussion remains general rather than providing a concrete assessment of how obstacles were managed. Hence, while factually cautious and relevant, it lacks the depth or specificity needed for a top score. | F15: =RIGHT(LEFT(E15,3),1) -> 2
A16: =_xlfn.CONCAT(C16,"_",D16) -> llama3.2_US293949_Q42 | B16: gpt-5-chat-latest | C16: llama3.2_US293949 | D16: Q42 | E16: **2** **Justification:** The conclusion portion of the answer is coherent, structured, and correctly identifies that the project lacks sufficient budgetary data to confirm financial control, notes possible humanresource overloads, and finds technical resources apparently adequate. These points address the question reasonably and are supported by the event log characteristics. However, it remains somewhat generic and assumes rather than demonstrates whether the project *did* stay within allocated resources. The analysis stops at identifying uncertainties instead of giving a definitive evidencebased assessment. Hence it is above average in relevance and clarity but not fully conclusive — deserving a **2** rather than the maximum **3**. | F16: =RIGHT(LEFT(E16,3),1) -> 2
A17: =_xlfn.CONCAT(C17,"_",D17) -> llama3.2_US293949_Q43 | B17: gpt-5-chat-latest | C17: llama3.2_US293949 | D17: Q43 | E17: **3** — The answer is wellstructured, clear, and demonstrates a solid understanding of project management best practices. It identifies several realistic improvement areas (prioritization, timelines, risk management, reviews, communication) and links them to their potential positive impacts on project outcomes. The suggestions are concrete, relevant to the provided event log, and balanced with a recognition of missing context. Overall, it meets all the criteria for a highquality, complete conclusion deserving the maximum grade. | F17: =RIGHT(LEFT(E17,3),1) -> 3
... A21: =_xlfn.CONCAT(C21,"_",D21) -> llama3.2_US293949_Q47 | B21: gpt-5-chat-latest | C21: llama3.2_US293949 | D21: Q47 | E21: **3** The final conclusions are clear, structured, and wellaligned with the project data and the prompt’s goal (advice for future teams). The points provided are concrete, relevant to project management best practices, and directly connected to observed issues—such as timing, dependencies, and coordination. The recommendations are actionable and comprehensive, without being generic filler. Overall, this is a complete and highquality final answer deserving the maximum grade. | F21: =RIGHT(LEFT(E21,3),1) -> 3
A22: =_xlfn.CONCAT(C22,"_",D22) -> llama3.2_US37581_285851_293949_Q48 | B22: gpt-5-chat-latest | C22: llama3.2_US37581_285851_293949 | D22: Q48 | E22: 3 – The final conclusion is accurate and well justified. It correctly identifies that the data provided (event log of tasks, dates, and durations) does not include any explicit indicators of schedule adherence or budget consumption, and therefore it is not possible to determine whether the projects were completed on time or within budget. The reasoning is sound and the conclusion is appropriate given the available information. | F22: 3
A23: =_xlfn.CONCAT(C23,"_",D23) -> llama3.2_US37581_285851_293949_Q49 | B23: gpt-5-chat-latest | C23: llama3.2_US37581_285851_293949 | D23: Q49 | E23: **Grade: 1** **Rationale:** The answer does make a minimal attempt to identify possible delays by referencing specific activity IDs (e.g., AR 41, AR 42–44). However, it misreads parts of the data — the event logs clearly include both start and finish dates for every task, so saying “no completion date mentioned” or “expected completion dates are not mentioned” is inaccurate. It also fails to identify genuine performance bottlenecks visible in the data (e.g., very long tasks like “Confirmar/garantir fonte orçamentária — 55 days,” or “Acompanhar as atividades pós implantação — 22–30 days”). No meaningful analysis of causes is provided beyond generic statements. Overall, the conclusions are incomplete and not well grounded in the given dataset. | F23: 1
A24: =_xlfn.CONCAT(C24,"_",D24) -> llama3.2_US37581_285851_293949_Q50 | B24: gpt-5-chat-latest | C24: llama3.2_US37581_285851_293949 | D24: Q50 | E24: **2** The conclusion is reasonably clear and balanced. It recognizes both achievements (objectives largely met, many tasks completed) and issues (delays, weak dependencies, resource constraints). The assessment roughly corresponds to a “moderate adherence” interpretation. However, it stays general and lacks direct evidence from the event log to substantiate claims (e.g., examples of delayed tasks or timeline deviation), so it does not demonstrate strong analytical grounding. Therefore, it merits a **2/3** — solid but not fully evidencebased or precise. | F24: =RIGHT(LEFT(E24,3),1) -> 2
A25: =_xlfn.CONCAT(C25,"_",D25) -> llama3.2_US37581_285851_293949_Q51 | B25: gpt-5-chat-latest | C25: llama3.2_US37581_285851_293949 | D25: Q51 | E25: **2** The conclusion provides a reasonable, coherent answer — it identifies that no explicit issues appear in the plans, then infers possible management and governance gaps (change, risk, contingency, and communication). It’s logically sound, consistent with the prompt, and supports the evaluation with practical improvement suggestions. However, it doesn’t extract concrete examples from the event logs (e.g., long task durations or delays as evidence of issues), which limits the specificity of the analysis. The response shows understanding and interpretation but lacks direct data-based justification, thus meriting a solid but not top score. | F25: =RIGHT(LEFT(E25,3),1) -> 2
A26: =_xlfn.CONCAT(C26,"_",D26) -> llama3.2_US37581_285851_293949_Q52 | B26: gpt-5-chat-latest | C26: llama3.2_US37581_285851_293949 | D26: Q52 | E26: **1** The conclusion correctly acknowledges that insufficient data prevents a definitive assessment of whether the projects stayed within the allocated human, financial, and technical resources. However, it remains largely generic and speculative, with no evidence-based analysis or reference to the event log data. While it recognizes the data limitations (which is accurate), it doesn’t extract or infer any meaningful insight from the available project information. Thus, it shows minimal analytical contribution beyond pointing out missing information — deserving a low but not zero score. | F26: =RIGHT(LEFT(E26,3),1) -> 1
A27: =_xlfn.CONCAT(C27,"_",D27) -> llama3.2_US37581_285851_293949_Q53 | B27: gpt-5-chat-latest | C27: llama3.2_US37581_285851_293949 | D27: Q53 | E27: **3** The final conclusions are well structured, comprehensive, and directly address realistic improvement areas grounded in standard project management best practices. The points are clear, actionable, and relevant to the scenario described (timeline management, dependencies, updates, resource allocation, risk management, QA, and stakeholder communication). There are no apparent factual or logical gaps. It demonstrates a complete understanding of how to improve project outcomes. | F27: =RIGHT(LEFT(E27,3),1) -> 3
A28: =_xlfn.CONCAT(C28,"_",D28) -> llama3.2_US37581_285851_293949_Q54 | B28: gpt-5-chat-latest | C28: llama3.2_US37581_285851_293949 | D28: Q54 | E28: **Grade: 1** **Justification:** The final answer correctly acknowledges that there isn’t enough information to conclusively determine whether all milestones were achieved as planned. While this is a reasonable and factually coherent conclusion given the data, the response does not explicitly address the question using the event log provided or demonstrate any analysis of milestone completion within the available evidence. It remains generic and procedural rather than evaluative. Thus, it shows partial understanding and minimal application of available data — earning a **1 (below average but not incorrect)** on the 0–3 scale. | F28: 1
A29: =_xlfn.CONCAT(C29,"_",D29) -> llama3.2_US37581_285851_293949_Q55 | B29: gpt-5-chat-latest | C29: llama3.2_US37581_285851_293949 | D29: Q55 | E29: **3** The final recommendations are clear, structured, and actionable. They address key aspects of project management — milestones and timelines, resource allocation, dependencies, plan updates, frameworks, accountability, and tools — all of which are relevant given the event log data and the patterns of task delays and coordination complexity. The answer demonstrates good synthesis of lessons learned from the projects and translates them into practical guidance for future initiatives. | F29: =RIGHT(LEFT(E29,3),1) -> 3
A30: =_xlfn.CONCAT(C30,"_",D30) -> llama3.2_US37581_285851_293949_Q56 | B30: gpt-5-chat-latest | C30: llama3.2_US37581_285851_293949 | D30: Q56 | E30: **3** The final conclusions are clear, wellstructured, and directly address lessons learned in project scope management. They identify realistic scheduling, resource allocation, task validation, dependency planning, and clear scope definition — all key aspects of effective scope management. The observations align with issues visible in the event log and translate them into actionable lessons. The reasoning is coherent and complete, so this deserves the maximum score. | F30: =RIGHT(LEFT(E30,3),1) -> 3
A31: =_xlfn.CONCAT(C31,"_",D31) -> llama3.2_US37581_285851_293949_Q57 | B31: gpt-5-chat-latest | C31: llama3.2_US37581_285851_293949 | D31: Q57 | E31: **3** The final conclusions are comprehensive, relevant, and well structured. The advice directly addresses project management best practices such as goal clarity, timeline realism, risk management, stakeholder communication, contingency planning, phased delivery, monitoring progress, quality assurance, defining roles, and incorporating lessons learned. These recommendations are general but meaningful and clearly rooted in common issues visible in the provided project logs (delays, unclear responsibilities, long task durations). Overall, it demonstrates a strong understanding and provides actionable guidance — deserving the maximum score. | F31: =RIGHT(LEFT(E31,3),1) -> 3
A32: =_xlfn.CONCAT(C32,"_",D32) -> llama3.2_US37581_Q18 | B32: gpt-5-chat-latest | C32: llama3.2_US37581 | D32: Q18 | E32: **2** The final conclusion appropriately recognizes that the event log does not include data about actual completion status or costs, and that therefore one cannot determine definitively whether the project was on time or within budget. That is correct and relevant. However, the answer drifts into speculation (“likely completed on time,” “could indicate efficient resource allocation”), which weakens the analytical precision. It shows basic understanding and partial justification but relies on conjecture rather than evidence — thus it deserves a *2* on the 0–3 scale. | F32: =RIGHT(LEFT(E32,3),1) -> 2
A33: =_xlfn.CONCAT(C33,"_",D33) -> llama3.2_US37581_Q19 | B33: gpt-5-chat-latest | C33: llama3.2_US37581 | D33: Q19 | E33: **2** The final conclusions of the answer are **accurate in a general sense** — they correctly note the lack of explicit baseline timelines and identify typical causes of delay (resource constraints, dependencies, complexity). The reasoning is **methodologically sound** and acknowledges the limitation of the available data. However, the answer does **not engage directly with the event log** to identify where delays might actually have occurred (e.g., long gaps between tasks, long durations such as the 10-day “Montar DSOL” or the 22-day “Acompanhar atividades pós-implantação”). It remains **too generic** and avoids specific observations that the data could support. Thus, the answer shows partial understanding (sound logic but weak application to the dataset), meriting a **grade of 2 out of 3**. | F33: =RIGHT(LEFT(E33,3),1) -> 2
A34: =_xlfn.CONCAT(C34,"_",D34) -> llama3.2_US37581_Q20 | B34: gpt-5-chat-latest | C34: llama3.2_US37581 | D34: Q20 | E34: **2** **Explanation:** The final conclusions are coherent and moderately supported by the data provided. The answer reasonably infers that the project adhered to the plan overall, acknowledging minor delays and data limitations. It shows a fair understanding of schedule adherence and task completion. However, it lacks deeper analysis of the evident longer tasks (e.g., “Montar DSOL”, “Certificação da Implantação”, “Acompanhar atividades pós-implantação”) and does not connect these delays explicitly to performance or adherence issues. The reasoning is sound but somewhat generic and does not fully leverage the detailed event log. | F34: =RIGHT(LEFT(E34,3),1) -> 2
A35: =_xlfn.CONCAT(C35,"_",D35) -> llama3.2_US37581_Q21 | B35: gpt-5-chat-latest | C35: llama3.2_US37581 | D35: Q21 | E35: **2** – The answer demonstrates a reasonable understanding of the question and offers plausible inferences about potential issues and how they might have been managed. While it correctly acknowledges that there’s no explicit mention of unexpected problems in the event log, it goes beyond that by identifying plausible risk areas (backup, monitoring) and proposing appropriate management strategies (change management, reviews, contingency plans). However, it relies heavily on speculation rather than evidence from the provided data, so it lacks the depth or direct linkage to concrete events needed for the highest score. | F35: =RIGHT(LEFT(E35,3),1) -> 2
A36: =_xlfn.CONCAT(C36,"_",D36) -> llama3.2_US37581_Q22 | B36: gpt-5-chat-latest | C36: llama3.2_US37581 | D36: Q22 | E36: **Grade: 1** **Reasoning:** The final part of the answer correctly recognizes that the available data (event log/project plan) does not contain explicit information about *resource allocation* in human, financial, or technical terms, and therefore a definitive conclusion cannot be drawn. This acknowledgement is valid and demonstrates some understanding of the task’s constraints. However, it falls short in the following ways: - It does **not provide any concrete evaluation** or inference based on the data that *is* available (e.g., consistency of task durations, absence of overlapping assignments suggesting resource strain, or possible indicators of staying within bounds). - The answer remains **generic and exploratory**, focusing on what should be analyzed rather than drawing a conclusion relevant to the question. - There is no synthesis of observed evidence or final judgment (e.g., “insufficient data to conclude, but no signs of resource overuse are evident”). Thus, while methodologically correct in its caution, it offers limited evaluative value and minimal insight—warranting a low but nonzero score. | F36: 1
A37: =_xlfn.CONCAT(C37,"_",D37) -> llama3.2_US37581_Q23 | B37: gpt-5-chat-latest | C37: llama3.2_US37581 | D37: Q23 | E37: **3** The final conclusions are clear, structured, and strongly aligned with best practices in project management. The answer identifies multiple actionable improvement areas — timeline precision, dependency mapping, detailed task breakdown, monitoring, risk management, stakeholder communication, and contingency planning. Each point is relevant to the provided project plan and logically tied to improving performance and outcomes. The recommendations show a solid understanding of project dynamics and are expressed concisely and effectively. | F37: =RIGHT(LEFT(E37,3),1) -> 3
A38: =_xlfn.CONCAT(C38,"_",D38) -> llama3.2_US37581_Q24 | B38: gpt-5-chat-latest | C38: llama3.2_US37581 | D38: Q24 | E38: **2** The final conclusions are partially correct — the answer recognizes that not all milestones appear to have been achieved as planned and points out timeline inconsistencies and delays. However, it remains vague and does not reference specific milestones or evidence from the event log to support the claim. The reasoning is general and speculative rather than data-driven. It shows moderate understanding but lacks concrete verification or precise analysis, which keeps it from a top score. | F38: =RIGHT(LEFT(E38,3),1) -> 2
A39: =_xlfn.CONCAT(C39,"_",D39) -> llama3.2_US37581_Q25 | B39: gpt-5-chat-latest | C39: llama3.2_US37581 | D39: Q25 | E39: **3** The answer gives a clear, wellstructured, and relevant set of recommendations that directly address potential improvements for future projects. It covers key aspects such as acceptance criteria, plan adjustments, QA emphasis, standardization, communication, and adds thoughtful bestpractice suggestions (agile, PM tools, change management). The advice is actionable and coherent with the context of the project plan. Overall, it fully meets the expectations for a strong, comprehensive conclusion. | F39: =RIGHT(LEFT(E39,3),1) -> 3
A40: =_xlfn.CONCAT(C40,"_",D40) -> llama3.2_US37581_Q26 | B40: gpt-5-chat-latest | C40: llama3.2_US37581 | D40: Q26 | E40: **3** The final conclusions clearly identify concrete and relevant lessons about project scope management, such as scope creep, unclear boundaries, lack of testing, and insufficient documentation. The improvement suggestions directly address these issues with actionable recommendations (better scope definition, review, prioritization, testing, documentation). The response demonstrates solid understanding and logical connection to the project context, meeting the maximum criteria for completeness and relevance. | F40: =RIGHT(LEFT(E40,3),1) -> 3
A41: =_xlfn.CONCAT(C41,"_",D41) -> llama3.2_US37581_Q27 | B41: gpt-5-chat-latest | C41: llama3.2_US37581 | D41: Q27 | E41: **3** The final conclusions are clear, structured, and practical. The advice addresses key project management dimensions—planning, change management, testing, communication, postimplementation followup, and technical debt—each linked logically to observable issues in the log. The recommendations are actionable and framed in a way that future teams can realistically apply. Overall, it demonstrates a comprehensive understanding of project improvement based on the provided experience. | F41: =RIGHT(LEFT(E41,3),1) -> 3
A42: =_xlfn.CONCAT(C42,"_",D42) -> gpt-4o_US285851_Q28 | B42: gpt-5-chat-latest | C42: gpt-4o_US285851 | D42: Q28 | E42: **3** The conclusion is accurate, wellreasoned, and clearly justified given the available data. It correctly notes that the event log does not contain baseline schedule or budget information, so a definitive answer cannot be given. It also highlights observed longduration tasks that *could* indicate delays, while avoiding unwarranted assumptions. The response is complete, precise, and appropriately cautious—fully meeting expectations for this type of analysis. | F42: =RIGHT(LEFT(E42,3),1) -> 3
A43: =_xlfn.CONCAT(C43,"_",D43) -> gpt-4o_US285851_Q29 | B43: gpt-5-chat-latest | C43: gpt-4o_US285851 | D43: Q29 | E43: **3** The final conclusions accurately identify the main delay ("Confirmar/garantir fonte orçamentária" – 55 days) and correctly interpret it as a bottleneck likely related to budget approval or coordination issues. It also distinguishes between genuinely delayed tasks and those that are long but expected (e.g., postimplementation monitoring). The reasoning is wellaligned with the data and demonstrates good understanding of project analysis. | F43: =RIGHT(LEFT(E43,3),1) -> 3
A44: =_xlfn.CONCAT(C44,"_",D44) -> gpt-4o_US285851_Q30 | B44: gpt-5-chat-latest | C44: gpt-4o_US285851 | D44: Q30 | E44: **3** The final conclusion is clear, coherent, and well supported by details from the event log. It correctly identifies the major deviation (the 55day budget confirmation delay), acknowledges extended tasks such as the 30day monitoring phase, and explains that most other activities followed the planned structure and durations. The reasoning links observed delays to likely causes (budget bottlenecks, coordination issues) and concludes with practical implications (improving budgeting and risk assessment). Overall, it provides a precise and balanced evaluation consistent with the prompt’s objectives. | F44: =RIGHT(LEFT(E44,3),1) -> 3
A45: =_xlfn.CONCAT(C45,"_",D45) -> gpt-4o_US285851_Q31 | B45: gpt-5-chat-latest | C45: gpt-4o_US285851 | D45: Q31 | E45: **3** The final conclusions effectively identify concrete issues (budget confirmation delay, task repetition, overlapping technical work) supported by evidence from the event log, and they clearly explain how these obstacles were managed (through planning, coordination, and structured closure processes). The answer demonstrates solid understanding and provides a coherent link between observed delays and their management, fitting the top grade on the 0–3 scale. | F45: =RIGHT(LEFT(E45,3),1) -> 3
A46: =_xlfn.CONCAT(C46,"_",D46) -> gpt-4o_US285851_Q32 | B46: gpt-5-chat-latest | C46: gpt-4o_US285851 | D46: Q32 | E46: **3** The final conclusion is accurate, well-reasoned, and aligns with the scope of the provided event log. It correctly observes that the data does not include baseline resource allocations, making it impossible to definitively assess compliance with human, financial, or technical resource constraints. The answer also identifies relevant indicators (e.g., unusually long task duration) and clearly explains what additional information would be required for a definitive assessment. Overall, it demonstrates complete understanding and sound reasoning based on the available evidence. | F46: =RIGHT(LEFT(E46,3),1) -> 3
A47: =_xlfn.CONCAT(C47,"_",D47) -> gpt-4o_US285851_Q33 | B47: gpt-5-chat-latest | C47: gpt-4o_US285851 | D47: Q33 | E47: **3** The conclusion is clear, well-structured, and demonstrates a solid understanding of the project’s weaknesses and potential improvements. It correctly identifies the key delay (“Confirmar/garantir fonte orçamentária”), suggests realistic and actionable improvements (process optimization, parallelization, better communication and planning), and connects these recommendations to observed data in the event log. The reasoning is coherent and comprehensive, with no major gaps. Overall, it fully meets the expectations for a top-grade answer. | F47: =RIGHT(LEFT(E47,3),1) -> 3
A48: =_xlfn.CONCAT(C48,"_",D48) -> gpt-4o_US285851_Q34 | B48: gpt-5-chat-latest | C48: gpt-4o_US285851 | D48: Q34 | E48: **3** The final conclusion is balanced, clear, and logically derived from the data. It recognizes potential outlier durations (55-day budget confirmation and 30-day post-implementation) while acknowledging that, without a baseline or planned schedule, it’s impossible to confirm deviations. The reasoning appropriately qualifies the answer and ties it back to whether milestones were “as planned.” It is thorough, consistent, and well contextualized—worthy of the maximum grade. | F48: =RIGHT(LEFT(E48,3),1) -> 3
... A85: =_xlfn.CONCAT(C85,"_",D85) -> gpt-3.5-turbo_US285851_Q31 | B85: gpt-5-chat-latest | C85: gpt-3.5-turbo_US285851 | D85: Q31 | E85: **3** The answer accurately identifies key unexpected issues (notably the 55day delay in confirming the budget source and the comparatively long 5day CMDB verification) and links them to plausible causes. It also explains, in a clear and realistic manner, how such delays could have been managed through coordination, communication, and escalation. The reasoning is concise, grounded in the event log, and complete — meeting the criteria for the highest grade. | F85: =RIGHT(LEFT(E85,3),1) -> 3
A86: =_xlfn.CONCAT(C86,"_",D86) -> gpt-3.5-turbo_US285851_Q32 | B86: gpt-5-chat-latest | C86: gpt-3.5-turbo_US285851 | D86: Q32 | E86: **Grade: 2** **Rationale:** The conclusion is coherent and positively answers the question, noting that human, financial, and technical resources were well managed according to the event log. However, the answer lacks critical evaluation or evidence of how resource usage was assessed—there is little discussion of possible risk points (e.g., the 55-day budget confirmation delay) or explicit references to performance deviations. It provides a general and reasonable conclusion but doesn’t demonstrate deeper analytical insight or specific justification from the data. | F86: 2
A87: =_xlfn.CONCAT(C87,"_",D87) -> gpt-3.5-turbo_US285851_Q33 | B87: gpt-5-chat-latest | C87: gpt-3.5-turbo_US285851 | D87: Q33 | E87: **3** — The answer clearly and succinctly identifies multiple relevant improvement areas (resource allocation, task dependency management, communication, performance monitoring, and risk management). Each point is coherent, realistic, and directly connected to improving project outcomes in the given context. While not deeply analytical, it is complete, structured, and actionable, fully meeting the expectations for the highest score. | F87: =RIGHT(LEFT(E87,3),1) -> 3
A88: =_xlfn.CONCAT(C88,"_",D88) -> gpt-3.5-turbo_US285851_Q34 | B88: gpt-5-chat-latest | C88: gpt-3.5-turbo_US285851 | D88: Q34 | E88: **3** The conclusion correctly answers the main question (“Were all project milestones achieved as planned?”) with a clear and justified “No.” It provides specific examples of tasks with significantly longer durations, directly supporting the reasoning about project delays. The evidence cited aligns with the event log, and the reasoning is coherent and relevant. Overall, it demonstrates complete understanding and solid justification, deserving the maximum score. | F88: =RIGHT(LEFT(E88,3),1) -> 3
A89: =_xlfn.CONCAT(C89,"_",D89) -> gpt-3.5-turbo_US285851_Q35 | B89: gpt-5-chat-latest | C89: gpt-3.5-turbo_US285851 | D89: Q35 | E89: **3** The final recommendations are clear, relevant, and well aligned with the issues evident in the event log. They address communication, bottlenecks, approvals, resource allocation, and continuous improvement—each directly related to the observed project delays (e.g., the 55day budget confirmation and multiple overlapping approvals). The suggestions are actionable and demonstrate a good understanding of project management improvement practices. | F89: =RIGHT(LEFT(E89,3),1) -> 3
A90: =_xlfn.CONCAT(C90,"_",D90) -> gpt-3.5-turbo_US285851_Q36 | B90: gpt-5-chat-latest | C90: gpt-3.5-turbo_US285851 | D90: Q36 | E90: **3** The conclusion clearly identifies a concrete lesson related to project scope management — the need to secure resources and confirm budget early to avoid major schedule delays. It correctly ties this insight to evidence in the event log (the 55day delay in Task5) and expands the point by linking it to stakeholder communication and coordination. The reasoning is relevant, specific, and complete, warranting the maximum grade on the 0–3 scale. | F90: =RIGHT(LEFT(E90,3),1) -> 3
A91: =_xlfn.CONCAT(C91,"_",D91) -> gpt-3.5-turbo_US285851_Q37 | B91: gpt-5-chat-latest | C91: gpt-3.5-turbo_US285851 | D91: Q37 | E91: **3** The final conclusions are clear, relevant, and wellgrounded in the project data. The answer identifies the main delay sources (budget confirmation, approvals, technical steps) and connects them to actionable recommendations such as early risk identification, improved communication, streamlined approvals, better progress monitoring, and planning for postimplementation tasks. These points fully address the prompt and demonstrate sound reasoning based on the project’s experience. | F91: =RIGHT(LEFT(E91,3),1) -> 3
A92: =_xlfn.CONCAT(C92,"_",D92) -> gpt-3.5-turbo_US293949_Q38 | B92: gpt-5-chat-latest | C92: gpt-3.5-turbo_US293949 | D92: Q38 | E92: **3** – The conclusion is accurate, wellreasoned, and complete given the available data. It correctly identifies schedule overruns (multiple tasks taking longer than expected) and appropriately notes that no cost data are available to judge the budget dimension. The reasoning aligns with the evidence in the event log and answers the prompt clearly. | F92: =RIGHT(LEFT(E92,3),1) -> 3
A93: =_xlfn.CONCAT(C93,"_",D93) -> gpt-3.5-turbo_US293949_Q39 | B93: gpt-5-chat-latest | C93: gpt-3.5-turbo_US293949 | D93: Q39 | E93: **3** The final conclusions clearly identify that delays occurred, list specific tasks affected, describe their duration and timing, and name the responsible resources. The explanation also outlines plausible root causes—resource constraints, dependencies, task complexity, or unexpected problems. The answer is consistent, detailed, and aligns with the project log evidence, meriting the maximum score. | F93: =RIGHT(LEFT(E93,3),1) -> 3
A94: =_xlfn.CONCAT(C94,"_",D94) -> gpt-3.5-turbo_US293949_Q40 | B94: gpt-5-chat-latest | C94: gpt-3.5-turbo_US293949 | D94: Q40 | E94: **3** The final conclusion accurately assesses that the project largely adhered to the plan and objectives, acknowledges moderate delays in specific technical tasks, and supports this with reasoning consistent with the event log. The evaluation is balanced and complete, reflecting a solid understanding of schedule adherence and overall project objectives — thus deserving the highest score on the 0–3 scale. | F94: =RIGHT(LEFT(E94,3),1) -> 3
A95: =_xlfn.CONCAT(C95,"_",D95) -> gpt-3.5-turbo_US293949_Q41 | B95: gpt-5-chat-latest | C95: gpt-3.5-turbo_US293949 | D95: Q41 | E95: **3** The final conclusions directly address the question by identifying specific delayed tasks from the event log (“Liberar regras de firewall”, “Cadastrar Servidor no GA - Windows”, etc.) and providing reasonable explanations such as dependencies, resource constraints, or technical issues. The response also clearly outlines how these were likely managed—through resource reallocation, timeline adjustment, expert consultation, and communication. The answer is coherent, evidence-based, and complete, justifying the maximum score. | F95: =RIGHT(LEFT(E95,3),1) -> 3
A96: =_xlfn.CONCAT(C96,"_",D96) -> gpt-3.5-turbo_US293949_Q42 | B96: gpt-5-chat-latest | C96: gpt-3.5-turbo_US293949 | D96: Q42 | E96: **Grade: 3** The conclusion is accurate, concise, and aligns well with the information provided. It correctly notes that human resource allocation appears adequate, identifies specific tasks ("Liberar regras de firewall") as performance outliers, and appropriately states that financial and technical resources cannot be assessed from the given data. The reasoning is sound and wellgrounded in the available evidence, with no major omissions or overreach. | F96: 3
A97: =_xlfn.CONCAT(C97,"_",D97) -> gpt-3.5-turbo_US293949_Q43 | B97: gpt-5-chat-latest | C97: gpt-3.5-turbo_US293949 | D97: Q43 | E97: **3** — The final conclusions are clear, coherent, and directly address the prompt. The answer identifies several well-founded improvement areas (resource allocation, task prioritization, efficiency, dependency management, communication, monitoring, and adaptability) that are all reasonable and realistic in the context of the event log provided. Each point is relevant to improving project performance and avoids generic or off-topic advice. The reasoning is comprehensive yet concise, showing strong understanding of project management improvement principles. | F97: =RIGHT(LEFT(E97,3),1) -> 3
A98: =_xlfn.CONCAT(C98,"_",D98) -> gpt-3.5-turbo_US293949_Q44 | B98: gpt-5-chat-latest | C98: gpt-3.5-turbo_US293949 | D98: Q44 | E98: **3** – The final conclusion directly and correctly answers the question (“No, not all project milestones were achieved as planned”) and provides a concise justification referring to delays and plausible causes. It is accurate, coherent, and complete given the available data. | F98: =RIGHT(LEFT(E98,3),1) -> 3
A99: =_xlfn.CONCAT(C99,"_",D99) -> gpt-3.5-turbo_US293949_Q45 | B99: gpt-5-chat-latest | C99: gpt-3.5-turbo_US293949 | D99: Q45 | E99: **3** The final recommendations are clear, well structured, and closely aligned with the project’s context. They address key lessons learned from the event log — such as resource allocation, task dependency management, communication, and monitoring of durations — all of which are relevant to improving performance in future projects. The suggestions are actionable, comprehensive, and realistic (e.g., introducing automation, conducting postproject reviews, strengthening QA). Overall, the concluding points demonstrate a thoughtful synthesis of insights and merit the highest grade on the 0–3 scale. | F99: =RIGHT(LEFT(E99,3),1) -> 3
A100: =_xlfn.CONCAT(C100,"_",D100) -> gpt-3.5-turbo_US293949_Q46 | B100: gpt-5-chat-latest | C100: gpt-3.5-turbo_US293949 | D100: Q46 | E100: **3** The final conclusions of the answer are clear, consistent, and directly related to project scope management. They accurately identify key lessons such as the need for better scope definition, control of scope creep, stronger change management, and appropriate resource allocation. The reasoning is aligned with the evidence from the event log and covers the main dimensions of scope management comprehensively. Overall, it is a complete, coherent, and wellfocused response deserving the maximum score. | F100: =RIGHT(LEFT(E100,3),1) -> 3
A101: =_xlfn.CONCAT(C101,"_",D101) -> gpt-3.5-turbo_US293949_Q47 | B101: gpt-5-chat-latest | C101: gpt-3.5-turbo_US293949 | D101: Q47 | E101: **3** The final conclusions are clear, comprehensive, and well-aligned with the project’s context. The advice covers key project management best practices—bottleneck identification, communication, resource allocation, process optimization, risk management, monitoring, and lessons learned—all of which are relevant to the given event log and its performance issues. The answer is structured, actionable, and captures the main insights expected from reflecting on the project execution, thus deserving the maximum grade. | F101: =RIGHT(LEFT(E101,3),1) -> 3
A102: =_xlfn.CONCAT(C102,"_",D102) -> gpt-3.5-turbo_US37581_285851_293949_Q48 | B102: gpt-5-chat-latest | C102: gpt-3.5-turbo_US37581_285851_293949 | D102: Q48 | E102: **3** The final answer correctly identifies that the event logs alone do not provide explicit information about whether the projects were completed on time or within budget. It reasonably explains what additional data would be required (baseline timeline, budget constraints) and supports the conclusion by referencing relevant facts in the logs (task durations, resource use, variability between projects). The reasoning is accurate, complete, and appropriately cautious, matching the question’s demands. | F102: =RIGHT(LEFT(E102,3),1) -> 3
A103: =_xlfn.CONCAT(C103,"_",D103) -> gpt-3.5-turbo_US37581_285851_293949_Q49 | B103: gpt-5-chat-latest | C103: gpt-3.5-turbo_US37581_285851_293949 | D103: Q49 | E103: **3** The final conclusions are accurate and coherent. The answer correctly identifies that all three projects experienced delays, provides relevant examples of tasks with longer durations, and offers plausible and contextually appropriate causes — such as resource constraints, technical and coordination challenges, and dependencies between teams. The synthesis is structured, aligns with the event log evidence, and demonstrates a sound understanding of project management factors affecting performance. | F103: =RIGHT(LEFT(E103,3),1) -> 3
A104: =_xlfn.CONCAT(C104,"_",D104) -> gpt-3.5-turbo_US37581_285851_293949_Q50 | B104: gpt-5-chat-latest | C104: gpt-3.5-turbo_US37581_285851_293949 | D104: Q50 | E104: **2** The answer correctly identifies that the three projects experienced schedule deviations and provides specific task examples suggesting poor adherence to the plan. However, the analysis is somewhat superficial — it restates durations rather than comparing them meaningfully to “planned” baselines (which aren’t explicitly given), and conclusions remain general (“faced challenges” without identifying root causes or impacts). Overall, it demonstrates partial understanding and acceptable reasoning, but lacks depth and substantiation required for a top score. | F104: =RIGHT(LEFT(E104,3),1) -> 2
A105: =_xlfn.CONCAT(C105,"_",D105) -> gpt-3.5-turbo_US37581_285851_293949_Q51 | B105: gpt-5-chat-latest | C105: gpt-3.5-turbo_US37581_285851_293949 | D105: Q51 | E105: **3** The final conclusions are coherent, specific, and grounded in the event log data. They accurately identify unexpected issues (e.g., task delays in CMDB updates, budget confirmation, monitoring implementation) and describe how project managers managed them (through timeline extensions, change requests, and resource adjustments). The explanation links observed delays with reasonable management actions, demonstrating understanding and evidence-based reasoning. Overall, it provides a complete and well-supported answer deserving the maximum score. | F105: =RIGHT(LEFT(E105,3),1) -> 3
A106: =_xlfn.CONCAT(C106,"_",D106) -> gpt-3.5-turbo_US37581_285851_293949_Q52 | B106: gpt-5-chat-latest | C106: gpt-3.5-turbo_US37581_285851_293949 | D106: Q52 | E106: **Grade: 3** The conclusion is accurate, coherent, and wellsupported by the information in the event log. It correctly identifies that not all projects stayed within allocated resources, points to specific examples of longduration tasks suggesting possible overruns, and reasonably emphasizes time management and resource utilization issues. The reasoning is aligned with the data and demonstrates an appropriate analytical depth for the question. | F106: 3
A107: =_xlfn.CONCAT(C107,"_",D107) -> gpt-3.5-turbo_US37581_285851_293949_Q53 | B107: gpt-5-chat-latest | C107: gpt-3.5-turbo_US37581_285851_293949 | D107: Q53 | E107: **3** The final conclusions are clear, relevant, and actionable. The answer correctly identifies coordination and communication as major improvement areas—consistent with the observed pattern of delays and long task durations across resources. It also proposes concrete, realistic measures (regular meetings, shared timelines, early bottleneck detection, contingency planning). The suggestions directly address performance issues implied by the log and would plausibly improve project outcomes. | F107: =RIGHT(LEFT(E107,3),1) -> 3
A108: =_xlfn.CONCAT(C108,"_",D108) -> gpt-3.5-turbo_US37581_285851_293949_Q54 | B108: gpt-5-chat-latest | C108: gpt-3.5-turbo_US37581_285851_293949 | D108: Q54 | E108: **Grade: 2** **Justification:** The conclusion correctly identifies that all three projects experienced delays and offers a coherent list of broad causal factors — resource allocation, client approval, technical tasks, certification, and postimplementation followup. These align reasonably well with the patterns observable in the event logs. However, the answer does not explicitly address the first question — whether all milestones were achieved as planned — nor does it reference any specific project IDs, tasks, or timing evidence from the logs to substantiate its claims. The reasoning remains general and qualitative, lacking analytical depth or concrete examples of delay duration or deviation. In summary, the response demonstrates a solid but not detailed understanding of delay causes; it would merit a **2** on a 0–3 scale for partial accuracy and limited evidence support. | F108: 2
A109: =_xlfn.CONCAT(C109,"_",D109) -> gpt-3.5-turbo_US37581_285851_293949_Q55 | B109: gpt-5-chat-latest | C109: gpt-3.5-turbo_US37581_285851_293949 | D109: Q55 | E109: **3** The final recommendations are clear, relevant, and directly applicable to the issues observed in the event logs. They address key recurring factors of delay — such as poor timeline communication, resource bottlenecks, slow approvals, and lack of ongoing monitoring — and propose concrete, actionable improvements. The addition of continuous learning through postproject reviews further strengthens the response. Overall, the answer demonstrates good synthesis and practical insight without redundancy. | F109: =RIGHT(LEFT(E109,3),1) -> 3
A110: =_xlfn.CONCAT(C110,"_",D110) -> gpt-3.5-turbo_US37581_285851_293949_Q56 | B110: gpt-5-chat-latest | C110: gpt-3.5-turbo_US37581_285851_293949 | D110: Q56 | E110: **3** The final conclusions are coherent, clearly aligned with the concept of project scope management, and supported by plausible observations from the event log. The answer correctly identifies the importance of scope definition, control of scope creep, stakeholder communication, and risk anticipation—all central lessons from scope management. The response is structured, relevant, and complete, showing understanding beyond superficial statements. | F110: =RIGHT(LEFT(E110,3),1) -> 3
A111: =_xlfn.CONCAT(C111,"_",D111) -> gpt-3.5-turbo_US37581_285851_293949_Q57 | B111: gpt-5-chat-latest | C111: gpt-3.5-turbo_US37581_285851_293949 | D111: Q57 | E111: **3** The final recommendations are clear, comprehensive, and well structured. They address core project management dimensions—communication, planning, resource allocation, monitoring, risk management, and continuous improvement—all directly relevant to the observed inefficiencies in the event log. The advice is actionable and aligned with best practices for preventing similar delays in future projects. | F111: =RIGHT(LEFT(E111,3),1) -> 3
A112: =_xlfn.CONCAT(C112,"_",D112) -> gpt-3.5-turbo_US37581_Q18 | B112: gpt-5-chat-latest | C112: gpt-3.5-turbo_US37581 | D112: Q18 | E112: **3** — The final conclusion is accurate, clear, and wellreasoned. It correctly identifies that the event log alone does not provide explicit information about deadlines or budget, and therefore a definitive assessment cannot be made. The answer demonstrates appropriate analytical reasoning and an understanding of what data would be necessary to make such a judgment. | F112: =RIGHT(LEFT(E112,3),1) -> 3
A113: =_xlfn.CONCAT(C113,"_",D113) -> gpt-3.5-turbo_US37581_Q19 | B113: gpt-5-chat-latest | C113: gpt-3.5-turbo_US37581 | D113: Q19 | E113: **3** The final conclusions accurately identify several significant delays (e.g., DSOL preparation, Certification, Backup, and Monitoring tasks), highlight the likely causes (complexity, underestimation, technical issues), and provide a coherent, evidencebased synthesis tied to the event log. While not exhaustive, the answer is complete and wellreasoned relative to the question prompt, deserving the maximum grade on the 0–3 scale. | F113: =RIGHT(LEFT(E113,3),1) -> 3
A114: =_xlfn.CONCAT(C114,"_",D114) -> gpt-3.5-turbo_US37581_Q20 | B114: gpt-5-chat-latest | C114: gpt-3.5-turbo_US37581 | D114: Q20 | E114: **Grade: 3** **Reasoning:** The final conclusion is accurate, coherent, and well-aligned with the event log. It identifies specific examples of delays, connects them to broader project performance issues (e.g., unforeseen challenges or resource constraints), and provides a balanced overall assessment. The reasoning correctly interprets deviations in task durations as evidence of partial non-adherence to the original plan and objectives. The answer demonstrates solid comprehension, clear justification, and appropriate use of evidence from the data—thus earning the maximum score. | F114: 3
A115: =_xlfn.CONCAT(C115,"_",D115) -> gpt-3.5-turbo_US37581_Q21 | B115: gpt-5-chat-latest | C115: gpt-3.5-turbo_US37581 | D115: Q21 | E115: **2** The answer correctly identifies several potential obstacles by referring to specific tasks that took longer or were repeated (“Montar DSOL,” “Atualizar o CMDB,” “Certificação da Implantação”). It also reasonably suggests general mitigation approaches such as reassessing priorities, adding resources, and maintaining communication. However, the response remains somewhat generic in describing how issues were managed — it doesn’t clearly tie the management actions to concrete evidence in the log (e.g., overlapping tasks, reallocation of resources, or delayed dependencies). It demonstrates fair reasoning and plausible inference but lacks the depth, specificity, and evidence-based connection that would justify a top score. | F115: =RIGHT(LEFT(E115,3),1) -> 2
A116: =_xlfn.CONCAT(C116,"_",D116) -> gpt-3.5-turbo_US37581_Q22 | B116: gpt-5-chat-latest | C116: gpt-3.5-turbo_US37581 | D116: Q22 | E116: **3** The final conclusion is accurate, well-reasoned, and directly answers the question. It correctly identifies that the event log does not contain information about resource allocation or budgets, so it is impossible to determine if the project stayed within them. The reasoning is logically consistent and reflects a solid understanding of the data limitations, warranting the maximum grade. | F116: =RIGHT(LEFT(E116,3),1) -> 3
A117: =_xlfn.CONCAT(C117,"_",D117) -> gpt-3.5-turbo_US37581_Q23 | B117: gpt-5-chat-latest | C117: gpt-3.5-turbo_US37581 | D117: Q23 | E117: **3** The conclusion is clear, structured, and directly addresses the question. It identifies several key improvement areas—resource allocation, dependency management, communication, risk management, monitoring, and training—that are both relevant and actionable in the context of an IT infrastructure project. The answer demonstrates a comprehensive understanding of project management principles and provides practical recommendations that could realistically improve outcomes. While it could be more specific to the given event log, its completeness and logical coherence warrant the maximum score. | F117: =RIGHT(LEFT(E117,3),1) -> 3
A118: =_xlfn.CONCAT(C118,"_",D118) -> gpt-3.5-turbo_US37581_Q24 | B118: gpt-5-chat-latest | C118: gpt-3.5-turbo_US37581 | D118: Q24 | E118: **3** The final conclusions are accurate, concise, and supported by evidence from the event log. The answer correctly identifies that while several milestones were achieved on time, others (e.g., *Montar DSOL* and *Certificação da Implantação*) experienced delays, leading to the clear conclusion that not all project milestones were achieved as planned. The reasoning is sound, balanced, and directly addresses the question. | F118: =RIGHT(LEFT(E118,3),1) -> 3
A119: =_xlfn.CONCAT(C119,"_",D119) -> gpt-3.5-turbo_US37581_Q25 | B119: gpt-5-chat-latest | C119: gpt-3.5-turbo_US37581 | D119: Q25 | E119: **3** The final recommendations are clear, structured, and directly connected to managing project execution and mitigating delays. They cover essential best practices (planning, communication, risk assessment, resource management, monitoring, and continuous improvement). The response is comprehensive, actionable, and aligned with insights that would logically arise from reviewing the provided event log. It demonstrates good understanding and provides practical guidance, fully meeting the prompt’s expectations. | F119: =RIGHT(LEFT(E119,3),1) -> 3
A120: =_xlfn.CONCAT(C120,"_",D120) -> gpt-3.5-turbo_US37581_Q26 | B120: gpt-5-chat-latest | C120: gpt-3.5-turbo_US37581 | D120: Q26 | E120: **3** — The final conclusions clearly address lessons learned on project scope management, emphasizing the importance of well-defined and communicated scope, continuous monitoring, and adaptation during execution. The answer demonstrates understanding of scope control and evaluation based on the event log and connects these ideas to improving future projects. It is complete, coherent, and aligned with the question. | F120: =RIGHT(LEFT(E120,3),1) -> 3
A121: =_xlfn.CONCAT(C121,"_",D121) -> gpt-3.5-turbo_US37581_Q27 | B121: gpt-5-chat-latest | C121: gpt-3.5-turbo_US37581 | D121: Q27 | E121: **3** The answer provides a clear, wellstructured, and comprehensive set of recommendations that directly address the lessons learned from the event log. The advice touches on all major aspects of project management — planning, communication, resource allocation, monitoring, risk management, and continuous improvement. Although somewhat generic, it is complete, relevant, and actionable, demonstrating sound understanding of project execution dynamics. | F121: =RIGHT(LEFT(E121,3),1) -> 3
A122: =_xlfn.CONCAT(C122,"_",D122) -> qwen3_US285851_Q28 | B122: gpt-5-chat-latest | C122: qwen3_US285851 | D122: Q28 | E122: **3** – The conclusion is accurate, clear, and appropriately qualified. It correctly notes that the deliverables appear completed on time according to the event log while identifying that budget information is unavailable and therefore cannot be assessed. The reasoning is consistent with the evidence provided and avoids unsupported assumptions. | F122: =RIGHT(LEFT(E122,3),1) -> 3
A123: =_xlfn.CONCAT(C123,"_",D123) -> qwen3_US285851_Q29 | B123: gpt-5-chat-latest | C123: qwen3_US285851 | D123: Q29 | E123: **3** The conclusions are clear, wellgrounded in the event log, and correctly identify which tasks took significantly longer than typical. The answer links those long durations to plausible causes—budget approval bureaucracy, documentation/compliance workload, resource and certification processes—and summarizes lessons learned. It is specific, coherent, and directly answers the question with justified reasoning. | F123: =RIGHT(LEFT(E123,3),1) -> 3
A124: =_xlfn.CONCAT(C124,"_",D124) -> qwen3_US285851_Q30 | B124: gpt-5-chat-latest | C124: qwen3_US285851 | D124: Q30 | E124: **2** The final answer provides a clear and wellstructured discussion of adherence to the plan. It correctly identifies major delays (the 55day funding step, repeated CMDB updates, and the 30day postimplementation work) and reasonably concludes that although the objectives were met, the schedule slipped. However, it somewhat overstates conclusions without direct evidence of the original “expected” dates, and it could more explicitly separate factual observations from inferred judgments about adherence. Overall, solid and mostly accurate, but not fully precise — thus a **2**. | F124: =RIGHT(LEFT(E124,3),1) -> 2
A125: =_xlfn.CONCAT(C125,"_",D125) -> qwen3_US285851_Q31 | B125: gpt-5-chat-latest | C125: qwen3_US285851 | D125: Q31 | E125: 3 The final conclusions clearly identify the key unexpected issues (notably the 55day funding approval and 30day postimplementation monitoring), explain why these were likely problematic, and describe plausible management or mitigation actions. The reasoning is consistent with the event log and well structured, giving a full and credible account of both the obstacles and how they were handled. | F125: 3
A126: =_xlfn.CONCAT(C126,"_",D126) -> qwen3_US285851_Q32 | B126: gpt-5-chat-latest | C126: qwen3_US285851 | D126: Q32 | E126: **3** The conclusion is detailed, specific, and wellaligned with the available evidence. It identifies concrete indicators of resource strain (notably the 55day and 30day tasks), explains how they point to human and process inefficiencies, and reasonably infers financial or technical pressures despite limited data. The reasoning is coherent and supported by the event log, directly addressing the question about staying within allocated resources. | F126: =RIGHT(LEFT(E126,3),1) -> 3
A127: =_xlfn.CONCAT(C127,"_",D127) -> qwen3_US285851_Q33 | B127: gpt-5-chat-latest | C127: qwen3_US285851 | D127: Q33 | E127: **3** – The conclusion is wellstructured, specific, and comprehensive. It clearly identifies major bottlenecks (budget approval, CMDB updates, redundant tasks, postimplementation delays) and proposes concrete corrective actions such as streamlining approvals, automating processes, improving communication, and optimizing scheduling/parallelization. The reasoning is coherent, supported by evidence from the event log, and focused on actionable improvements. Overall, it demonstrates a clear understanding of the problem and offers practical solutions consistent with good projectmanagement principles. | F127: =RIGHT(LEFT(E127,3),1) -> 3
A128: =_xlfn.CONCAT(C128,"_",D128) -> qwen3_US285851_Q34 | B128: gpt-5-chat-latest | C128: qwen3_US285851 | D128: Q34 | E128: **3** The final conclusion is clear, coherent, and well supported by evidence from the event log. It correctly identifies that all milestones appear to have been achieved according to the provided schedule, highlights key tasks (validation, certification, closure), and explains the reasoning concisely. The explanation is consistent, with no contradictions or major omissions. | F128: =RIGHT(LEFT(E128,3),1) -> 3
A129: =_xlfn.CONCAT(C129,"_",D129) -> qwen3_US285851_Q35 | B129: gpt-5-chat-latest | C129: qwen3_US285851 | D129: Q35 | E129: **3** The final answer provides a clear, structured, and evidencebased set of recommendations that directly relate to issues visible in the event log. It identifies specific longduration and repeated tasks, discusses likely causes (e.g., approval delays, redundant documentation, late security involvement), and offers concrete, actionable improvements (streamlining approvals, automating processes, early security engagement, better estimation, and communication). The recommendations are comprehensive and relevant, showing a good balance between analysis and practicality—fully aligned with what the prompt requested. | F129: =RIGHT(LEFT(E129,3),1) -> 3
A130: =_xlfn.CONCAT(C130,"_",D130) -> qwen3_US285851_Q36 | B130: gpt-5-chat-latest | C130: qwen3_US285851 | D130: Q36 | E130: **3** The final conclusions are clear, wellstructured, and directly address project scope management lessons. They identify specific patterns in the event log (e.g., redundant tasks, long approvals, compliance delays) and translate them into actionable lessons: clearer scope definition, avoiding overlap, early stakeholder alignment, and managing compliance within the defined scope. The insights are coherent and relevant to the provided data, showing a thorough understanding of scoperelated issues and their impact on project performance. | F130: =RIGHT(LEFT(E130,3),1) -> 3
A131: =_xlfn.CONCAT(C131,"_",D131) -> qwen3_US285851_Q37 | B131: gpt-5-chat-latest | C131: qwen3_US285851 | D131: Q37 | E131: **3** The advice is comprehensive, wellstructured, and directly supported by evidence from the project log. It identifies specific longduration tasks, links them to likely root causes (e.g., budget approval, resource allocation, crossteam dependencies), and translates those observations into practical, clearly phrased recommendations. The coverage spans process optimization, coordination, tooling, training, and risk management. It demonstrates clear insight into how to prevent similar delays in future projects and thus merits the maximum grade. | F131: =RIGHT(LEFT(E131,3),1) -> 3
A132: =_xlfn.CONCAT(C132,"_",D132) -> qwen3_US293949_Q38 | B132: gpt-5-chat-latest | C132: qwen3_US293949 | D132: Q38 | E132: **3** The final conclusion is coherent and wellgrounded in the given data. It correctly identifies that the **project appears to have finished on time** (based on the final logged date) and that **budget performance cannot be evaluated** because no cost information is provided. It also briefly notes longer task durations as possible bottlenecks but distinguishes them from overall completion. The reasoning is clear, factbased, and complete for the available evidence. | F132: =RIGHT(LEFT(E132,3),1) -> 3
A133: =_xlfn.CONCAT(C133,"_",D133) -> qwen3_US293949_Q39 | B133: gpt-5-chat-latest | C133: qwen3_US293949 | D133: Q39 | E133: **3** The final part of the answer clearly identifies that there were delays, pinpoints where they occurred (certification, firewall setup, postimplementation monitoring), quantifies their durations using data from the log, and reasonably infers underlying causes such as approvals, configuration complexity, and resource dependencies. The reasoning is organized, specific, and aligned with the prompt’s request for patterns or factors causing delays. | F133: =RIGHT(LEFT(E133,3),1) -> 3
A134: =_xlfn.CONCAT(C134,"_",D134) -> qwen3_US293949_Q40 | B134: gpt-5-chat-latest | C134: qwen3_US293949 | D134: Q40 | E134: **2** – The final answer is detailed, coherent, and demonstrates a solid understanding of project execution versus planning. It accurately identifies which tasks experienced delays, analyzes patterns (e.g., resource bottlenecks, repeated activities, extended security tasks), and draws reasonable conclusions about deviation from the plan. However, it slightly overrelies on descriptive recaps and could be more concise and explicit about *how much* the project deviated from its original objectives, which keeps it just short of the maximum score. | F134: =RIGHT(LEFT(E134,3),1) -> 2
A135: =_xlfn.CONCAT(C135,"_",D135) -> qwen3_US293949_Q41 | B135: gpt-5-chat-latest | C135: qwen3_US293949 | D135: Q41 | E135: **3** The concluding answer clearly identifies specific unexpected issues (firewall rule delays, certification bottlenecks, extended postimplementation monitoring, repetitive CMDB updates), explains their likely causes, and describes how each was managed (extended timelines, collaboration, resource reallocation, documentation). It grounds these points in the event log using task numbers and durations, showing good analytical depth and coherence. The reasoning is wellstructured and aligns with the evidence given, deserving the maximum score. | F135: =RIGHT(LEFT(E135,3),1) -> 3
A136: =_xlfn.CONCAT(C136,"_",D136) -> qwen3_US293949_Q42 | B136: gpt-5-chat-latest | C136: qwen3_US293949 | D136: Q42 | E136: **3** The final answer is well-structured, provides clear reasoning, and explicitly ties observed delays and task overlaps to potential overuse or shortage of human and technical resources. It correctly notes the absence of financial data and draws a balanced conclusion. The analysis demonstrates good understanding of the event log and the limits of available information. Overall, it’s a complete and coherent response deserving the highest grade on the 0–3 scale. | F136: =RIGHT(LEFT(E136,3),1) -> 3
A137: =_xlfn.CONCAT(C137,"_",D137) -> qwen3_US293949_Q43 | B137: gpt-5-chat-latest | C137: qwen3_US293949 | D137: Q43 | E137: **3** The final conclusions are clear, structured, and directly address what could have improved the project outcome. They identify concrete performance issues (e.g., long firewall and certification phases, rework, 30day postimplementation delays) and propose specific, actionable remedies: better resource coordination, dependency mapping, realistic scheduling, automation, and stronger communication. The answer connects these recommendations to observed data and avoids vague or generic statements. Overall, it’s comprehensive, relevant, and well reasoned—worthy of the maximum score. | F137: =RIGHT(LEFT(E137,3),1) -> 3
... A145: =_xlfn.CONCAT(C145,"_",D145) -> qwen3_US37581_285851_293949_Q51 | B145: gpt-5-chat-latest | C145: qwen3_US37581_285851_293949 | D145: Q51 | E145: **2** The final conclusions are clear and grounded in the provided data. The answer correctly notes that no explicit unexpected issues are documented and that projects appear to have followed standard execution. It also identifies areas that *might* suggest performance variability (e.g., long durations or repeated tasks) without overinterpreting them. However, the explanation remains somewhat generic: it restates data rather than analyzing root causes or management actions in depth. A stronger answer would explicitly link longer task durations (e.g., “Confirmar fonte orçamentária – 55 days”) to possible procedural or approval bottlenecks and describe how they were likely managed (through extended coordination or approvals). | F145: =RIGHT(LEFT(E145,3),1) -> 2
A146: =_xlfn.CONCAT(C146,"_",D146) -> qwen3_US37581_285851_293949_Q52 | B146: gpt-5-chat-latest | C146: qwen3_US37581_285851_293949 | D146: Q52 | E146: 3 The conclusion appropriately notes that there is no direct data on allocated or actual resources—financial, human, or technical—and thus a firm determination cannot be made. It clearly distinguishes between the information available in the event log (timing and responsibilities) and what would be required to answer the resource allocation question. The reasoning is sound, concise, and logically consistent, making it a complete and accurate final answer deserving of the highest grade. | F146: 3
...

Sheet GP5_judge2
A1: Master Key | B1: model | C1: projectID | D1: questionID | E1: answer | F1: Grade
A2: =_xlfn.CONCAT(C2,"_",D2) -> llama3.2_US285851_Q28 | B2: gpt-5-chat-latest | C2: llama3.2_US285851 | D2: Q28 | E2: **3** The conclusion is clear, accurate, and directly addresses both elements of the question. It correctly notes that: - Most tasks were completed on time, but some (especially Task 5) took significantly longer, which may have affected the schedule. - The budget aspect cannot be evaluated because cost data are missing from the event log. The reasoning is aligned with the available evidence and avoids speculation beyond the data. It fully satisfies the evaluation criteria, so it deserves the maximum grade. | F2: =RIGHT(LEFT(E2,3),1) -> 3
A3: =_xlfn.CONCAT(C3,"_",D3) -> llama3.2_US285851_Q29 | B3: gpt-5-chat-latest | C3: llama3.2_US285851 | D3: Q29 | E3: **3** The conclusion accurately identifies the main delays (notably the 55day financing approval and 30day postimplementation followup), highlights repeated or overlapping tasks (CMDB updates, firewall activities), and reasonably infers causes such as duplication, coordination, and resource issues. It also provides coherent improvement suggestions. The response is wellfocused on project delays and causes, meeting the requirements for a top score. | F3: =RIGHT(LEFT(E3,3),1) -> 3
A4: =_xlfn.CONCAT(C4,"_",D4) -> llama3.2_US285851_Q30 | B4: gpt-5-chat-latest | C4: llama3.2_US285851 | D4: Q30 | E4: **Grade: 2** **Rationale:** The final conclusions summarize the project’s adherence moderately well: they correctly identify delays (notably Task5), duplication (Tasks29and39), and general adherence issues. The answer provides reasonable qualitative and quantitative judgments (“task efficiency60%,resourceutilization70%”) and practical improvement suggestions. However, it lacks stronger linkage between observed evidence and the overarching “original plan and objectives.” The numerical ratings appear arbitrary rather than clearly derived, and the analysis does not fully articulate whether the project met its intended functional or business outcomes. In short, it’s a fair, partially substantiated evaluation—better than minimal but not consistently rigorous. | F4: 2
A5: =_xlfn.CONCAT(C5,"_",D5) -> llama3.2_US285851_Q31 | B5: gpt-5-chat-latest | C5: llama3.2_US285851 | D5: Q31 | E5: **3** The answer provides a clear, coherent evaluation grounded in the event log. It identifies the main long-duration task (Task5) as a potential issue, notes possible rework or repetition, and explains that although there were delays, they were manageable and did not significantly disrupt the project. The conclusion directly addresses the question (“were there unexpected issues or obstacles, and how were they managed?”) and supports its claims with relevant observations from the data. Overall, the reasoning is complete and accurate, fitting the top mark on the 0–3 scale. | F5: =RIGHT(LEFT(E5,3),1) -> 3
A6: =_xlfn.CONCAT(C6,"_",D6) -> llama3.2_US285851_Q32 | B6: gpt-5-chat-latest | C6: llama3.2_US285851 | D6: Q32 | E6: **2** The conclusion is reasonably well supported and demonstrates some understanding of resource utilization (identifying long task durations and possible inefficiencies). It links those delays to potential human and financial resource issues while acknowledging the lack of full data for a definitive conclusion. However, it does not make a clear, direct statement answering whether the project *stayed within* allocated resources—it only suggests possible underutilization or inefficiency. The analysis is partially complete but not conclusive, hence a good but not top score. | F6: =RIGHT(LEFT(E6,3),1) -> 2
A7: =_xlfn.CONCAT(C7,"_",D7) -> llama3.2_US285851_Q33 | B7: gpt-5-chat-latest | C7: llama3.2_US285851 | D7: Q33 | E7: **3** The final conclusions are coherent, relevant, and well-aligned with the event log. They identify concrete improvement areas (task breakdown, dependency management, resource allocation, and monitoring) and propose reasonable corrective actions grounded in sound project management practices. The reasoning is consistent with the data provided and demonstrates understanding of where inefficiencies and bottlenecks occurred. | F7: =RIGHT(LEFT(E7,3),1) -> 3
A8: =_xlfn.CONCAT(C8,"_",D8) -> llama3.2_US285851_Q34 | B8: gpt-5-chat-latest | C8: llama3.2_US285851 | D8: Q34 | E8: **2** **Explanation:** The final conclusion correctly states that most project milestones were achieved as planned, while acknowledging some delays and duplicated or overlapping tasks. It demonstrates a reasonable understanding of the event log and identifies relevant evidence (e.g., duplicate tasks, unusual durations). However, it stops short of providing clear evidence that milestones were verified against a predetermined plan or specific milestone criteria. The reasoning is sound but lacks depth and precise linkage between findings and milestone achievement. Overall, the answer is **mostly correct and reasonable**, but not fully thorough — hence a **grade of 2 out of 3**. | F8: =RIGHT(LEFT(E8,3),1) -> 2
A9: =_xlfn.CONCAT(C9,"_",D9) -> llama3.2_US285851_Q35 | B9: gpt-5-chat-latest | C9: llama3.2_US285851 | D9: Q35 | E9: **3** The final recommendations are clear, structured, and directly address the issues identified in the event log. They propose practical measures—such as better use of project management tools, improved resource allocation, dependency management, and regular monitoring—to mitigate similar delays in future projects. The suggestions are comprehensive, cover both process and communication improvements, and demonstrate sound understanding of project management best practices. | F9: =RIGHT(LEFT(E9,3),1) -> 3
A10: =_xlfn.CONCAT(C10,"_",D10) -> llama3.2_US285851_Q36 | B10: gpt-5-chat-latest | C10: llama3.2_US285851 | D10: Q36 | E10: **3** The final conclusions effectively address lessons related to **project scope management** using clear evidence from the event log. The answer identifies repeated and overlapping tasks (Tasks17,39), points to unclear ownership and evolving requirements, and ties these to **scope creep, lack of clarity in deliverables, and poor communication**—all central to scope management lessons. It also notes anomalies (like zeroday validation) as indicators of weak task control and documentation. Overall, the response demonstrates solid understanding and specificity, fully meeting expectations for insight on scope definition and control. | F10: =RIGHT(LEFT(E10,3),1) -> 3
A11: =_xlfn.CONCAT(C11,"_",D11) -> llama3.2_US285851_Q37 | B11: gpt-5-chat-latest | C11: llama3.2_US285851 | D11: Q37 | E11: **3** – The answer provides a wellstructured, insightful, and evidencebased set of recommendations that directly reflect the event log issues. It correctly identifies the unusually long task duration as a bottleneck, notes duplicated resource effort, emphasizes communication improvement, suggests automation for repetitive activities, and recommends continuous plan review. These points are accurate, relevant, and actionable. The reasoning aligns clearly with information from the project log and demonstrates a thorough understanding of performance factors. | F11: =RIGHT(LEFT(E11,3),1) -> 3
A12: =_xlfn.CONCAT(C12,"_",D12) -> llama3.2_US293949_Q38 | B12: gpt-5-chat-latest | C12: llama3.2_US293949 | D12: Q38 | E12: **2** – The conclusion is mostly accurate and demonstrates reasonable understanding of the event log. It correctly notes that some tasks exceeded typical durations and highlights potential delays and inefficiencies. It also appropriately acknowledges the lack of sufficient data to make a definitive claim about schedule and budget compliance. However, it could be more concise and better structured in summarizing the findings. The reasoning is sound but not fully precise or datadriven enough to merit the highest grade. | F12: =RIGHT(LEFT(E12,3),1) -> 2
A13: =_xlfn.CONCAT(C13,"_",D13) -> llama3.2_US293949_Q39 | B13: gpt-5-chat-latest | C13: llama3.2_US293949 | D13: Q39 | E13: **3** The final conclusions are coherent, well-structured, and fully aligned with the prompt's objective. The answer correctly identifies delays, specifies which tasks were affected, and provides plausible, multifactor explanations — long durations, task repetition, dependencies, and resource constraints — all derived from the event log. The reasoning is comprehensive and accurate without major omissions or factual errors. | F13: =RIGHT(LEFT(E13,3),1) -> 3
A14: =_xlfn.CONCAT(C14,"_",D14) -> llama3.2_US293949_Q40 | B14: gpt-5-chat-latest | C14: llama3.2_US293949 | D14: Q40 | E14: **2** The final conclusion adequately summarizes the project’s adherence as “moderate,” noting both ontime and delayed tasks and identifying performance issues causing deviations. The reasoning is coherent and consistent with the event log’s data. However, it lacks clear quantitative benchmarks or deeper linkage to project objectives beyond timing, making it more descriptive than analytical. Thus, the answer is solid but not fully detailed or comprehensive—worthy of a **2/3**. | F14: =RIGHT(LEFT(E14,3),1) -> 2
A15: =_xlfn.CONCAT(C15,"_",D15) -> llama3.2_US293949_Q41 | B15: gpt-5-chat-latest | C15: llama3.2_US293949 | D15: Q41 | E15: **2** The answer correctly identifies key tasks with longer-than-expected durations (specifically the firewall-related tasks and reporting tasks) and plausibly interprets them as unexpected obstacles. It also suggests reasonable generic management responses (rescheduling, reallocating resources, stakeholder communication, troubleshooting). However, the explanation remains somewhat general and not fully grounded in the provided event log beyond noting delays, lacking any specific reference to concrete corrective actions or observed adaptations in the schedule. Therefore, it shows good but not excellent analytical connection between evidence and interpretation. | F15: =RIGHT(LEFT(E15,3),1) -> 2
A16: =_xlfn.CONCAT(C16,"_",D16) -> llama3.2_US293949_Q42 | B16: gpt-5-chat-latest | C16: llama3.2_US293949 | D16: Q42 | E16: **2** The final conclusion is coherent, cautious, and grounded in the data from the event log. It correctly notes that certain tasks (notably firewall rule implementation and postdeployment monitoring) took unusually long and could indicate stretched human or technical resources. It also appropriately highlights the lack of financial or budgetary data, so a definitive conclusion cannot be made. However, the answer remains somewhat general and qualitative—it identifies performance issues but does not explicitly connect them to concrete evidence of exceeding financial or human resource allocations. It could improve by synthesizing these observations into a clearer, more decisive judgment about whether the project stayed within or exceeded its resources. | F16: =RIGHT(LEFT(E16,3),1) -> 2
A17: =_xlfn.CONCAT(C17,"_",D17) -> llama3.2_US293949_Q43 | B17: gpt-5-chat-latest | C17: llama3.2_US293949 | D17: Q43 | E17: **3** The final conclusions are clear, relevant, and directly aligned with the event log evidence. The answer identifies concrete performance issues (firewall approval delays, long certification, postimplementation monitoring) and translates them into actionable improvement steps — addressing bottlenecks, dependencies, and parallelization. It also provides managerial recommendations (workflow optimization, agile methods) that logically follow from the analysis. The reasoning is coherent and comprehensive enough to merit the maximum score. | F17: =RIGHT(LEFT(E17,3),1) -> 3
A18: =_xlfn.CONCAT(C18,"_",D18) -> llama3.2_US293949_Q44 | B18: gpt-5-chat-latest | C18: llama3.2_US293949 | D18: Q44 | E18: **Grade: 2** **Reasoning:** The final conclusions correctly identify that some tasks show irregular durations (both unusually long and unusually short) and that these deviations could signal potential performance or planning issues. The answer appropriately acknowledges uncertainty and lack of context. However, the analysis includes some inaccuracies—for instance, there is no explicit evidence in the log that task #20 extended to July 6, and tasks largely appear to have been completed within the logged periods without clear “planned vs. actual” comparison data. The response also fails to directly address the main question (“Were all milestones achieved as planned?”) with a definitive yes/no conclusion. Overall, it shows a good understanding of issues in the data but lacks precision and direct alignment with the prompt’s requested conclusion—hence a midhigh score of **2**. | F18: 2
A19: =_xlfn.CONCAT(C19,"_",D19) -> llama3.2_US293949_Q45 | B19: gpt-5-chat-latest | C19: llama3.2_US293949 | D19: Q45 | E19: **3** The final conclusions are wellstructured, clear, and directly grounded in the evidence from the event log. The recommendations (identifying critical path activities, standardizing procedures, automating repetitive tasks, monitoring progress, and applying structured methodologies) are all relevant, specific, and actionable. They demonstrate strong understanding of both project management and process improvement. There are no major gaps or misinterpretations, so this deserves the maximum score. | F19: =RIGHT(LEFT(E19,3),1) -> 3
A20: =_xlfn.CONCAT(C20,"_",D20) -> llama3.2_US293949_Q46 | B20: gpt-5-chat-latest | C20: llama3.2_US293949 | D20: Q46 | E20: **3** The final conclusions clearly identify relevant lessons learned about project scope management based on evidence from the event log. The points about underestimated task scope, unclear expectations, and insufficient resource allocation directly relate to scope management challenges. The reasoning logically connects task durations with scope control issues, and the summary provides actionable insights for improvement. Overall, it is coherent, relevant, and complete, fully meeting the intent of the question. | F20: =RIGHT(LEFT(E20,3),1) -> 3
A21: =_xlfn.CONCAT(C21,"_",D21) -> llama3.2_US293949_Q47 | B21: gpt-5-chat-latest | C21: llama3.2_US293949 | D21: Q47 | E21: **3** The final conclusions provide a clear, structured, and relevant set of recommendations directly based on the event log data. The advice addresses multiple key aspects — performance issues, resource management, progress monitoring, quality assurance, automation, and communication. Each point is actionable and grounded in the context of the observed project execution. Overall, it demonstrates comprehensive understanding and sound reasoning, fully meeting the task's expectations. | F21: =RIGHT(LEFT(E21,3),1) -> 3
A22: =_xlfn.CONCAT(C22,"_",D22) -> llama3.2_US37581_285851_293949_Q48 | B22: gpt-5-chat-latest | C22: llama3.2_US37581_285851_293949 | D22: Q48 | E22: **2** The conclusion appropriately notes that the information provided is insufficient to determine whether deliverables were completed on time and within budget, acknowledging gaps in data (deadlines, budgets). The reasoning is cautious and factually sound, avoiding unsupported assumptions. However, it doesn’t make full or precise use of the event log to infer performance patterns or timing consistency between projects — it stays quite general. Thus, it demonstrates partial understanding and justified caution but lacks depth or specific analysis needed for a top score. | F22: =RIGHT(LEFT(E22,3),1) -> 2
A23: =_xlfn.CONCAT(C23,"_",D23) -> llama3.2_US37581_285851_293949_Q49 | B23: gpt-5-chat-latest | C23: llama3.2_US37581_285851_293949 | D23: Q49 | E23: **Grade: 1** **Reasoning:** The final conclusions of the answer are mostly generic and overlook clear evidence of delays in the provided event logs. For instance, in project **US285851**, the task *“Confirmar/garantir fonte orçamentária (FOI doador)”* took **55 days**, which is a significant delay when compared with typical task durations (1–5 days). Similarly, other long-running activities such as *“Acompanhar as atividades pós implantação”* (22 to 30 days) also suggest extended durations indicating possible bottlenecks or delays. The evaluated answer incorrectly claims there were “no significant delays” and fails to identify these anomalies or analyze probable causes, such as dependency on external approvals, resource allocation issues, or sequential handovers. While the response is coherent and structured, it lacks accuracy and depth regarding the core question. | F23: 1
A24: =_xlfn.CONCAT(C24,"_",D24) -> llama3.2_US37581_285851_293949_Q50 | B24: gpt-5-chat-latest | C24: llama3.2_US37581_285851_293949 | D24: Q50 | E24: **1** The final portion of the provided answer does not directly evaluate adherence to the plan and objectives in a decisive way. It primarily notes the lack of information and gives generic project management observations without synthesizing the event log data into a conclusion. While it correctly acknowledges uncertainty and identifies potential issues (e.g., delays, resource use), it does not concretely state **how well** the project adhered to the original plan. Therefore, it shows some understanding but lacks specific, actionable evaluation — meriting a low-to-medium score on the 0–3 scale. | F24: =RIGHT(LEFT(E24,3),1) -> 1
A25: =_xlfn.CONCAT(C25,"_",D25) -> llama3.2_US37581_285851_293949_Q51 | B25: gpt-5-chat-latest | C25: llama3.2_US37581_285851_293949 | D25: Q51 | E25: **3** The final conclusions are coherent, clearly identify plausible unexpected issues (delays in CF approval, installations, backup, patching, and ticket closure), and describe concrete, reasonable management actions (timeline adjustments, vendor consultation, prioritization, coordination with support teams). The response interprets the event logs credibly, links issues to their management approaches, and conveys a complete understanding of how the problems were mitigated. Overall, it is accurate, wellreasoned, and consistent with the prompt—meriting the maximum score. | F25: =RIGHT(LEFT(E25,3),1) -> 3
A26: =_xlfn.CONCAT(C26,"_",D26) -> llama3.2_US37581_285851_293949_Q52 | B26: gpt-5-chat-latest | C26: llama3.2_US37581_285851_293949 | D26: Q52 | E26: **3** The final conclusion in the provided answer is accurate, well-reasoned, and directly supported by the evidence. It correctly identifies that the available event log lacks explicit data on resource allocation, utilization, or financial metrics—making it impossible to determine whether the projects stayed within allocated resources. The explanation is clear, logically consistent with the given data, and appropriately cautious in its conclusion. | F26: =RIGHT(LEFT(E26,3),1) -> 3
A27: =_xlfn.CONCAT(C27,"_",D27) -> llama3.2_US37581_285851_293949_Q53 | B27: gpt-5-chat-latest | C27: llama3.2_US37581_285851_293949 | D27: Q53 | E27: **2** The answer provides a set of relevant and coherent generic improvement suggestions that demonstrate a reasonable understanding of project management principles (e.g., resource allocation, risk management, communication, adaptability, and lessons learned). However, it remains quite general and does not draw on any specific evidence or patterns from the provided event logs (such as delays in specific tasks or recurring bottlenecks tied to certain roles or dependencies). The conclusions are logically structured and actionable at a high level but lack contextual depth or data-driven insights that would elevate it to the highest grade. | F27: =RIGHT(LEFT(E27,3),1) -> 2
A28: =_xlfn.CONCAT(C28,"_",D28) -> llama3.2_US37581_285851_293949_Q54 | B28: gpt-5-chat-latest | C28: llama3.2_US37581_285851_293949 | D28: Q54 | E28: **2** **Reasoning:** The conclusion offers a reasonable and partially supported assessment based on the visible data — it recognizes project completion differences and acknowledges limitations in available information. However, it does not clearly or conclusively relate to whether **milestones were achieved as planned** (the core of the prompt), and the justification remains somewhat general. It demonstrates partial understanding and moderate analysis quality but lacks precision and completeness for the highest score. | F28: =RIGHT(LEFT(E28,3),1) -> 2
A29: =_xlfn.CONCAT(C29,"_",D29) -> llama3.2_US37581_285851_293949_Q55 | B29: gpt-5-chat-latest | C29: llama3.2_US37581_285851_293949 | D29: Q55 | E29: **3** – The answer provides a thorough, structured, and relevant set of recommendations directly applicable to the context of IT infrastructure projects. The conclusions are clear, actionable, and align well with common project management best practices (requirements clarity, phased planning, risk management, resource allocation, communication, and iterative improvement). Although somewhat generic, the recommendations are comprehensive and demonstrate an understanding of the issues implied by the event logs. | F29: =RIGHT(LEFT(E29,3),1) -> 3
A30: =_xlfn.CONCAT(C30,"_",D30) -> llama3.2_US37581_285851_293949_Q56 | B30: gpt-5-chat-latest | C30: llama3.2_US37581_285851_293949 | D30: Q56 | E30: **3** The final conclusions are coherent, complete, and well aligned with established project scope management principles. The response identifies key weaknesses—such as lack of clear scope definition, requirement ambiguity, and scope creep—and translates them into actionable lessons aligned with best practices (clear scope statement, thorough planning, shared understanding, proper validation). It demonstrates a solid understanding of scope management concepts and communicates them clearly. | F30: =RIGHT(LEFT(E30,3),1) -> 3
A31: =_xlfn.CONCAT(C31,"_",D31) -> llama3.2_US37581_285851_293949_Q57 | B31: gpt-5-chat-latest | C31: llama3.2_US37581_285851_293949 | D31: Q57 | E31: **3** The final conclusions are comprehensive, wellstructured, and grounded in standard project management best practices. They clearly translate the experience into actionable advice—covering communication, risk management, task prioritization, plan updates, resource allocation, documentation of lessons, and scope control. The recommendations are relevant to the observed delays and coordination challenges apparent in the provided event logs. Overall, this is a complete, coherent, and highquality response deserving the maximum grade. | F31: =RIGHT(LEFT(E31,3),1) -> 3
A32: =_xlfn.CONCAT(C32,"_",D32) -> llama3.2_US37581_Q18 | B32: gpt-5-chat-latest | C32: llama3.2_US37581 | D32: Q18 | E32: **Grade: 2** **Justification:** The answer gives a reasonable and factually consistent interpretation of the event log — it correctly identifies that the project closed on 28/11/2024 and that all activities were concluded by that point. However, it is somewhat contradictory: it first claims “some deliverables were not completed on time” but then concludes that “no tasks were postponed or extended beyond their scheduled deadlines.” It also omits any mention of *budget* performance. While there is a basic understanding of timing, the final conclusion is incomplete and slightly inconsistent, so a midtogood score (2/3) is appropriate. | F32: 2
A33: =_xlfn.CONCAT(C33,"_",D33) -> llama3.2_US37581_Q19 | B33: gpt-5-chat-latest | C33: llama3.2_US37581 | D33: Q19 | E33: **2** The answer shows a **good understanding** of the task — it identifies specific activities that took longer than average and offers **plausible causes** for the delays such as resource constraints, technical dependencies, and complexity. It is mostly coherent and consistent with the data provided. However, it falls short of a top score (3) because: - It doesn’t **quantify or compare** durations relative to other tasks, so it's unclear whether the identified tasks truly represent outliers. - Some activities (e.g., 5day tasks) may be standard for those types of work, but this isn’t evaluated. - The conclusion is **generic**, mentioning common project delay causes rather than specific evidence from the log. Overall, the reasoning is solid but lacks deeper, evidencebased analysis — hence a **grade of 2/3**. | F33: =RIGHT(LEFT(E33,3),1) -> 2
A34: =_xlfn.CONCAT(C34,"_",D34) -> llama3.2_US37581_Q20 | B34: gpt-5-chat-latest | C34: llama3.2_US37581 | D34: Q20 | E34: **2** The final conclusions are reasonably aligned with the evidence in the event log and provide a balanced interpretation — the answer notes both on-time and delayed tasks, identifies dependencies, and correctly observes that adherence was mixed. However, it also contains factual inaccuracies (e.g., incorrect assumptions about overall completion date and specific task durations) and lacks clear reference to project objectives beyond scheduling. The reasoning is partially sound but not precise enough for the top grade. | F34: =RIGHT(LEFT(E34,3),1) -> 2
A35: =_xlfn.CONCAT(C35,"_",D35) -> llama3.2_US37581_Q21 | B35: gpt-5-chat-latest | C35: llama3.2_US37581 | D35: Q21 | E35: **3** The answer demonstrates a clear and wellstructured analysis directly linked to the event log. It identifies several tasks whose durations deviated from expectations, reasonably interprets them as possible obstacles, and comments on how they might have been managed given the available information. The reasoning is accurate, grounded in the data, and the conclusion appropriately notes the limits of the evidence. Minor missing details (e.g., specific corrective actions) prevent it from being exceptional, but overall the response is thorough and well aligned with the prompt’s intent. | F35: =RIGHT(LEFT(E35,3),1) -> 3
A36: =_xlfn.CONCAT(C36,"_",D36) -> llama3.2_US37581_Q22 | B36: gpt-5-chat-latest | C36: llama3.2_US37581 | D36: Q22 | E36: **2** The final conclusion is generally reasonable — it identifies likely issues (delays and extended task durations) and ties them to possible resource constraints. However, it is somewhat vague and lacks direct evidence from the event log demonstrating overuse of human, financial, or technical resources. The assessment remains qualitative rather than data-backed, but it correctly notes that extended durations could imply resource constraints. Hence, it deserves a **2**: adequate and coherent, but not comprehensive or strongly evidenced. | F36: =RIGHT(LEFT(E36,3),1) -> 2
A37: =_xlfn.CONCAT(C37,"_",D37) -> llama3.2_US37581_Q23 | B37: gpt-5-chat-latest | C37: llama3.2_US37581 | D37: Q23 | E37: **3** The final conclusions are structured, relevant, and directly address the prompt. The answer identifies concrete improvement areas (resource allocation, dependencies, communication, and workload balancing) and provides actionable recommendations (progress monitoring, task segmentation, capacity planning). The suggestions are realistic, align with the data in the event log, and demonstrate analytical thinking about project management practices. While not exceptionally detailed in quantifying impact, the response is comprehensive and wellreasoned, meriting the maximum grade. | F37: =RIGHT(LEFT(E37,3),1) -> 3
A38: =_xlfn.CONCAT(C38,"_",D38) -> llama3.2_US37581_Q24 | B38: gpt-5-chat-latest | C38: llama3.2_US37581 | D38: Q24 | E38: **2** The final conclusion correctly recognizes that the data provided is insufficient to determine definitively whether all milestones were achieved as planned, and it identifies some potentially delayed tasks. However, it lacks a clear, decisive answer about milestones (e.g., a direct “cannot confirm all were achieved as planned” or “possible delays found”), and does not tie the observations explicitly to milestone achievement rather than task duration. It shows reasonable analysis but falls short of a fully clear and conclusive evaluation — hence, a solid but not perfect grade. | F38: =RIGHT(LEFT(E38,3),1) -> 2
A39: =_xlfn.CONCAT(C39,"_",D39) -> llama3.2_US37581_Q25 | B39: gpt-5-chat-latest | C39: llama3.2_US37581 | D39: Q25 | E39: **3** The conclusions are clear, structured, and directly address the prompt’s requirement: they derive actionable recommendations grounded in the patterns from the event log. The advice (e.g., improving resource allocation, clarifying dependencies, enhancing testing, and formalizing change management) is specific, relevant, and demonstrates an understanding of project performance factors. The additional points on regular reviews, communication, and better scheduling tools strengthen the response. Overall, this is a complete, well-reasoned answer deserving of the highest score (3). | F39: =RIGHT(LEFT(E39,3),1) -> 3
A40: =_xlfn.CONCAT(C40,"_",D40) -> llama3.2_US37581_Q26 | B40: gpt-5-chat-latest | C40: llama3.2_US37581 | D40: Q26 | E40: **2** The final conclusions show a reasonable understanding of project scope management, connecting observed delays to issues of planning, resource allocation, and dependencies. However, the answer is mostly descriptive rather than analytical; it summarizes durations but doesn’t clearly articulate *specific lessons learned* about scope definition, control, or change management. The insights are logical but generic and lack depth in linking performance patterns directly to scope management practices. | F40: =RIGHT(LEFT(E40,3),1) -> 2
A41: =_xlfn.CONCAT(C41,"_",D41) -> llama3.2_US37581_Q27 | B41: gpt-5-chat-latest | C41: llama3.2_US37581 | D41: Q27 | E41: **3** The final conclusions are clear, relevant, and well-grounded in the event log. The advice covers several key project management dimensions — task dependency management, resource utilization, testing practices, stakeholder communication, contingency planning, and continuous improvement. Each point is justified with evidence from the project data, demonstrating a thoughtful analysis and actionable recommendations. It aligns closely with what one would expect from a high-quality project postmortem or lessons-learned summary. | F41: =RIGHT(LEFT(E41,3),1) -> 3
A42: =_xlfn.CONCAT(C42,"_",D42) -> gpt-4o_US285851_Q28 | B42: gpt-5-chat-latest | C42: gpt-4o_US285851 | D42: Q28 | E42: **2** The final conclusion demonstrates a clear understanding of the project’s timeline and identifies plausible sources of delay (notably the 55day funding confirmation). It correctly notes that there is insufficient data to confirm whether the project stayed within budget. The reasoning is coherent, evidencebased, and aligned with the available information. However, it falls short of a concise, definitive statement on delivery performance—it remains somewhat speculative about impacts and does not explicitly summarize whether the project met its planned schedule. Thus, it merits a **2** for being accurate and reasonably complete but not fully conclusive. | F42: =RIGHT(LEFT(E42,3),1) -> 2
A43: =_xlfn.CONCAT(C43,"_",D43) -> gpt-4o_US285851_Q29 | B43: gpt-5-chat-latest | C43: gpt-4o_US285851 | D43: Q29 | E43: **3** The final conclusions are coherent, specific, and well supported by evidence from the event log. The answer correctly identifies the 55day budget confirmation as a major delay, discusses other long or potentially blocking activities, and gives plausible underlying causes (budget approval, coordination, dependencies, compliance). It distinguishes between inherent task length and actual performance issues and ends with practical improvement suggestions. Overall, it demonstrates complete understanding and clear reasoning—worthy of the maximum score. | F43: =RIGHT(LEFT(E43,3),1) -> 3
A44: =_xlfn.CONCAT(C44,"_",D44) -> gpt-4o_US285851_Q30 | B44: gpt-5-chat-latest | C44: gpt-4o_US285851 | D44: Q30 | E44: **3** The final assessment is clear, coherent, and well-supported by evidence from the event log. It identifies key deviations (notably the prolonged budget confirmation phase and extended post-implementation monitoring), comments on resource allocation and task flow, and reaches a balanced conclusion: that the project largely adhered to objectives but faced timeline inefficiencies. The reasoning is consistent, complete, and directly answers how well the project adhered to the plan and objectives—making it a strong, high-quality response. | F44: =RIGHT(LEFT(E44,3),1) -> 3
... A55: =_xlfn.CONCAT(C55,"_",D55) -> gpt-4o_US293949_Q41 | B55: gpt-5-chat-latest | C55: gpt-4o_US293949 | D55: Q41 | E55: **3** The final conclusions clearly identify multiple unexpected issues or obstacles, link them to specific tasks in the event log, and provide plausible explanations for each (e.g., inter-team coordination, technical complexity, access permissions). The answer also comments on how these issues were managed—through additional time allocation, validation, and collaborative efforts—which fully addresses the prompt. The reasoning is coherent and grounded in the data from the log, deserving the highest score. | F55: =RIGHT(LEFT(E55,3),1) -> 3
A56: =_xlfn.CONCAT(C56,"_",D56) -> gpt-4o_US293949_Q42 | B56: gpt-5-chat-latest | C56: gpt-4o_US293949 | D56: Q42 | E56: **Grade: 3** The final conclusions are coherent, wellstructured, and grounded in evidence from the event log. The answer explicitly addresses all three resource dimensions—human, financial, and technical—and links observed delays (e.g., firewall rules, certification) to possible resource strain. The reasoning is consistent, balanced, and avoids unsupported claims. While it acknowledges the limitation of lacking direct financial data, it still provides a plausible assessment based on task duration patterns. Overall, it delivers a complete and logical conclusion aligned with the question’s requirements. | F56: 3
A57: =_xlfn.CONCAT(C57,"_",D57) -> gpt-4o_US293949_Q43 | B57: gpt-5-chat-latest | C57: gpt-4o_US293949 | D57: Q43 | E57: **3** The answer is well structured, comprehensive, and clearly addresses multiple relevant improvement areas based on the event log. It identifies specific issues (task sequencing, long durations, resource bottlenecks) and links them to actionable recommendations (parallelization, better resource management, automation, coordination, and risk planning). The reasoning is coherent, detailed, and directly aligned with the project scenario. It shows good analytical depth and provides practical, implementable suggestions—consistent with the highest rating on the provided scale. | F57: =RIGHT(LEFT(E57,3),1) -> 3
A58: =_xlfn.CONCAT(C58,"_",D58) -> gpt-4o_US293949_Q44 | B58: gpt-5-chat-latest | C58: gpt-4o_US293949 | D58: Q44 | E58: **3** The conclusion clearly states that all tasks were eventually completed but that some milestones likely experienced delays due to longer-than-expected durations in key technical areas (firewall, certification, monitoring). It succinctly answers the question—acknowledging project completion while noting deviations from the plan—and provides reasoning tied to observed task durations. This demonstrates a complete, accurate, and well-supported evaluation deserving of the maximum grade. | F58: =RIGHT(LEFT(E58,3),1) -> 3
A59: =_xlfn.CONCAT(C59,"_",D59) -> gpt-4o_US293949_Q45 | B59: gpt-5-chat-latest | C59: gpt-4o_US293949 | D59: Q45 | E59: **3** The final recommendations are clear, well-structured, and directly connected to observations from the event log. The answer identifies concrete pain points (such as tasks with unusually long durations, resource overlaps, and coordination challenges) and links them to actionable improvement areas including resource planning, communication, automation, and critical path management. The reasoning is aligned with typical project management best practices and demonstrates a comprehensive understanding of the log’s implications. Overall, the response is complete and appropriate for a top score. | F59: =RIGHT(LEFT(E59,3),1) -> 3
A60: =_xlfn.CONCAT(C60,"_",D60) -> gpt-4o_US293949_Q46 | B60: gpt-5-chat-latest | C60: gpt-4o_US293949 | D60: Q46 | E60: **3** The final conclusions are clear, coherent, and wellaligned with the prompt. They identify concrete lessons linked to **scope definition, dependency management, resource coordination, time estimation, flexibility, communication, and validation**, all grounded in the project’s eventlog evidence. The answer synthesizes the observed issues into meaningful scopemanagement insights rather than generic statements. It demonstrates solid understanding and supports each point with contextual examples. Overall, it fully meets the expectations for completeness and relevance. | F60: =RIGHT(LEFT(E60,3),1) -> 3
A61: =_xlfn.CONCAT(C61,"_",D61) -> gpt-4o_US293949_Q47 | B61: gpt-5-chat-latest | C61: gpt-4o_US293949 | D61: Q47 | E61: **3** The final recommendations are clear, relevant, and wellstructured. They draw direct connections between observed project delays (e.g., “Liberar regras de firewall,” “Certificação da Implantação”) and actionable advice. The response covers all key improvement areas—resource management, task parallelization, communication, process optimization, risk management, and documentation. The guidance is practical, grounded in the data, and comprehensive enough to merit the maximum grade. | F61: =RIGHT(LEFT(E61,3),1) -> 3
A62: =_xlfn.CONCAT(C62,"_",D62) -> gpt-4o_US37581_285851_293949_Q48 | B62: gpt-5-chat-latest | C62: gpt-4o_US37581_285851_293949 | D62: Q48 | E62: **2** The conclusion is reasonably wellfounded: it correctly notes that several tasks lasted much longer than others, signaling likely schedule slippage and possible budget impact, and it also acknowledges the absence of explicit cost or baseline schedule data. However, it stops short of a definite assessment (“appears there were… potential delays”) and doesn’t clearly connect timelines to an explicit definition of “on time and within budget.” The reasoning is sound but not conclusive enough for top marks. | F62: =RIGHT(LEFT(E62,3),1) -> 2
A63: =_xlfn.CONCAT(C63,"_",D63) -> gpt-4o_US37581_285851_293949_Q49 | B63: gpt-5-chat-latest | C63: gpt-4o_US37581_285851_293949 | D63: Q49 | E63: **3** The final conclusions of the answer are clear, detailed, and correctly supported by evidence from the event log. The response identifies specific tasks with abnormally long durations, explains their potential causes (complexity, coordination issues, financial approvals, postimplementation monitoring), and groups these causes into meaningful categories. It demonstrates both accuracy and insight while remaining wellstructured and aligned with the prompt’s request to detect patterns and reasons for delays. | F63: =RIGHT(LEFT(E63,3),1) -> 3
A64: =_xlfn.CONCAT(C64,"_",D64) -> gpt-4o_US37581_285851_293949_Q50 | B64: gpt-5-chat-latest | C64: gpt-4o_US37581_285851_293949 | D64: Q50 | E64: **3** The final conclusions are wellstructured, clear, and closely aligned with the question asked. The answer draws from task patterns in the logs, highlights major sources of delay (budget approval, firewall configuration, postimplementation), notes redundancies that might suggest rework, and connects these findings directly to overall adherence to plan and objectives. It shows synthesis and balanced evaluation rather than mere description, demonstrating a comprehensive understanding. | F64: =RIGHT(LEFT(E64,3),1) -> 3
A65: =_xlfn.CONCAT(C65,"_",D65) -> gpt-4o_US37581_285851_293949_Q51 | B65: gpt-5-chat-latest | C65: gpt-4o_US37581_285851_293949 | D65: Q51 | E65: **3** The final conclusions are detailed, accurate, and consistent with the event log data. The answer correctly identifies concrete examples of delays (e.g., the 55day budget confirmation in US285851 and the extended firewall configuration in US293949), interprets them as potential obstacles, and provides plausible management explanations. It shows understanding of dependencies and process implications without overreaching beyond the given data. Overall, it fully addresses the question and demonstrates clear reasoning grounded in evidence. | F65: =RIGHT(LEFT(E65,3),1) -> 3
A66: =_xlfn.CONCAT(C66,"_",D66) -> gpt-4o_US37581_285851_293949_Q52 | B66: gpt-5-chat-latest | C66: gpt-4o_US37581_285851_293949 | D66: Q52 | E66: **3** — The conclusion is accurate, wellreasoned, and clearly justified given the data. It correctly notes that the event log lacks financial and technical resource information, and it identifies the limits of what can be fairly concluded from the dataset while highlighting plausible indicators (e.g., unusually long task durations). The reasoning is sound and complete for the information provided, fully meeting the expectations of the question. | F66: =RIGHT(LEFT(E66,3),1) -> 3
A67: =_xlfn.CONCAT(C67,"_",D67) -> gpt-4o_US37581_285851_293949_Q53 | B67: gpt-5-chat-latest | C67: gpt-4o_US37581_285851_293949 | D67: Q53 | E67: **3** The final conclusions are comprehensive, actionable, and directly address the prompt’s focus on improving project outcomes based on the observed delays. The answer identifies concrete improvement areas—resource management, communication, process optimization, time management, training, and technology. Each suggestion is relevant to the event log evidence (e.g., long-duration tasks, dependencies across roles) and includes both strategic and operational measures. The recommendations are logically structured, feasible, and reflect a systems-level understanding of project execution dynamics, justifying the highest score on the scale. | F67: =RIGHT(LEFT(E67,3),1) -> 3
A68: =_xlfn.CONCAT(C68,"_",D68) -> gpt-4o_US37581_285851_293949_Q54 | B68: gpt-5-chat-latest | C68: gpt-4o_US37581_285851_293949 | D68: Q54 | E68: **3** The answer’s conclusion is accurate and wellreasoned: it correctly points out that the event log contains only actual execution data and no planned baseline or explicit milestone indicators, thus preventing a definitive assessment of whether milestones were achieved *as planned*. It also appropriately infers which activities might count as milestones and notes that they were completed within recorded timeframes. The reasoning is coherent, relevant to the question, and complete given the available data. | F68: =RIGHT(LEFT(E68,3),1) -> 3
... A91: =_xlfn.CONCAT(C91,"_",D91) -> gpt-3.5-turbo_US285851_Q37 | B91: gpt-5-chat-latest | C91: gpt-3.5-turbo_US285851 | D91: Q37 | E91: **3** The answer provides clear, structured, and relevant advice directly tied to lessons that can be inferred from the project’s event log. It addresses likely delay causes (e.g., approvals, resource allocation, communication), suggests practical mitigation actions, and includes improvement and review recommendations. The points are concise, actionable, and aligned with the prompt’s context, demonstrating full comprehension and value for future project teams. | F91: =RIGHT(LEFT(E91,3),1) -> 3
A92: =_xlfn.CONCAT(C92,"_",D92) -> gpt-3.5-turbo_US293949_Q38 | B92: gpt-5-chat-latest | C92: gpt-3.5-turbo_US293949 | D92: Q38 | E92: 3 — The final conclusion is accurate and appropriate given the data. It clearly states that the event log alone does not provide enough information to determine whether the project deliverables were on time or within budget, since planned baselines and budget data are missing. The reasoning is sound, concise, and directly answers the question’s uncertainty. | F92: 3
A93: =_xlfn.CONCAT(C93,"_",D93) -> gpt-3.5-turbo_US293949_Q39 | B93: gpt-5-chat-latest | C93: gpt-3.5-turbo_US293949 | D93: Q39 | E93: **3** The final conclusions accurately identify clear delays in the project (e.g., long durations for firewall rules, GA registration, infrastructure follow-up, and repeated certification tasks). The answer also provides reasonable, specific potential causes—coordination challenges, resource issues, and technical complexities—rather than vague or generic explanations. It demonstrates good alignment with the event log data and covers multiple relevant delays, showing a solid understanding of the problem. | F93: =RIGHT(LEFT(E93,3),1) -> 3
A94: =_xlfn.CONCAT(C94,"_",D94) -> gpt-3.5-turbo_US293949_Q40 | B94: gpt-5-chat-latest | C94: gpt-3.5-turbo_US293949 | D94: Q40 | E94: **2** The answer provides a reasonably accurate and concise evaluation, correctly identifying that the project had delays and some inconsistencies in resource assignments. It supports the conclusion with specific examples (“Liberar regras de firewall,” “Implementação de Backup,” and “Cadastrar Servidor no GA – Windows”). However, it remains somewhat generic and lacks a deeper analysis of how these issues impacted overall project objectives or schedule adherence in quantitative terms. Thus, it demonstrates good understanding but not full depth — meriting a **2** on a 0–3 scale. | F94: =RIGHT(LEFT(E94,3),1) -> 2
A95: =_xlfn.CONCAT(C95,"_",D95) -> gpt-3.5-turbo_US293949_Q41 | B95: gpt-5-chat-latest | C95: gpt-3.5-turbo_US293949 | D95: Q41 | E95: **3** The answer effectively identifies key delays in the project (e.g., firewall configuration, certification, monitoring implementation) and provides reasonable, evidence-based explanations grounded in the event log. It also offers a concise and plausible description of how these obstacles were likely managed—through communication, escalation, and coordination. The reasoning is coherent, tied to the data, and demonstrates understanding of project dynamics. | F95: =RIGHT(LEFT(E95,3),1) -> 3
A96: =_xlfn.CONCAT(C96,"_",D96) -> gpt-3.5-turbo_US293949_Q42 | B96: gpt-5-chat-latest | C96: gpt-3.5-turbo_US293949 | D96: Q42 | E96: **2** **Justification:** The answer correctly notes that the event log alone does not provide enough information to definitively determine whether the project stayed within human, financial, or technical resource limits. It also appropriately identifies potential indicators of resource constraints (delays and repeated tasks). However, the conclusion remains general and lacks deeper reasoning or clear judgment regarding resource usage. It is accurate but not fully developed—hence, a solid but not maximum score. | F96: =RIGHT(LEFT(E96,3),1) -> 2
A97: =_xlfn.CONCAT(C97,"_",D97) -> gpt-3.5-turbo_US293949_Q43 | B97: gpt-5-chat-latest | C97: gpt-3.5-turbo_US293949 | D97: Q43 | E97: **3** The final part of the answer is clear, well-structured, and includes multiple concrete improvement recommendations that directly address typical project efficiency and outcome issues (communication, resource allocation, scheduling, prioritization, monitoring, and risk management). The suggestions are relevant, actionable, and aligned with the prompt’s request to improve the project’s outcome. Hence, it deserves the maximum score. | F97: =RIGHT(LEFT(E97,3),1) -> 3
A98: =_xlfn.CONCAT(C98,"_",D98) -> gpt-3.5-turbo_US293949_Q44 | B98: gpt-5-chat-latest | C98: gpt-3.5-turbo_US293949 | D98: Q44 | E98: **Grade: 2** **Reasoning:** The final conclusion correctly identifies that *not all milestones were achieved as planned* and points out several tasks that took longer than expected, which aligns with the question’s goal. However, the justification shows some inconsistencies and assumptions — for instance, the statement claims exact extended durations (like “5 days instead of 3”) that are not explicitly supported by the provided data (the event log lists only start and finish dates, without baseline plan comparisons). Overall, the answer demonstrates understanding of project delay identification and provides relevant examples, but it slightly overinterprets the data and lacks precise evidence regarding planned vs. actual durations. Hence, it deserves a **2 (good but not fully accurate)** rating. | F98: 2
A99: =_xlfn.CONCAT(C99,"_",D99) -> gpt-3.5-turbo_US293949_Q45 | B99: gpt-5-chat-latest | C99: gpt-3.5-turbo_US293949 | D99: Q45 | E99: **3** The final recommendations are clear, structured, and relevant to the context of an IT infrastructure implementation project. They cover key project management improvement areas — resource allocation, planning, monitoring, communication, and continuous learning — all of which directly address potential delays observed in the event log. The conclusions are practical, comprehensive, and show a solid understanding of how to enhance future project performance. | F99: =RIGHT(LEFT(E99,3),1) -> 3
A100: =_xlfn.CONCAT(C100,"_",D100) -> gpt-3.5-turbo_US293949_Q46 | B100: gpt-5-chat-latest | C100: gpt-3.5-turbo_US293949 | D100: Q46 | E100: **3** The conclusions are clear, relevant, and well-aligned with project scope management principles. The answer identifies key lessons such as the importance of clear scope definition, controlling scope creep, managing dependencies, effective resource allocation, and continuous monitoring—all strongly supported by the event log data. The reasoning shows good synthesis of scope management theory with project evidence, demonstrating a complete and accurate understanding of the topic. | F100: =RIGHT(LEFT(E100,3),1) -> 3
A101: =_xlfn.CONCAT(C101,"_",D101) -> gpt-3.5-turbo_US293949_Q47 | B101: gpt-5-chat-latest | C101: gpt-3.5-turbo_US293949 | D101: Q47 | E101: **3** – The final conclusions are clear, structured, and directly address the prompt. The advice is relevant, actionable, and ties well to observed issues in the event log (delays, coordination, resource bottlenecks, estimation, monitoring, and documentation). The response provides balanced and comprehensive recommendations, showing good understanding of project management improvement based on the data. | F101: =RIGHT(LEFT(E101,3),1) -> 3
A102: =_xlfn.CONCAT(C102,"_",D102) -> gpt-3.5-turbo_US37581_285851_293949_Q48 | B102: gpt-5-chat-latest | C102: gpt-3.5-turbo_US37581_285851_293949 | D102: Q48 | E102: **3** The answer accurately identifies that the event logs do not provide sufficient information to determine whether the projects were completed on time or within budget. It correctly explains that while activity durations and resources are listed, data about planned deadlines and budget baselines are missing. The reasoning is clear, relevant, and complete given the available information. | F102: =RIGHT(LEFT(E102,3),1) -> 3
A103: =_xlfn.CONCAT(C103,"_",D103) -> gpt-3.5-turbo_US37581_285851_293949_Q49 | B103: gpt-5-chat-latest | C103: gpt-3.5-turbo_US37581_285851_293949 | D103: Q49 | E103: **Grade: 2** **Rationale:** The answer correctly identifies that there were delays and highlights one significantly delayed activity in each project (notably the 55day budgeting task in US285851). It also provides plausible causal explanations such as resource constraints and technical complexity. However, its analysis is only partially accurate and somewhat superficial: - It misinterprets some normallength tasks (e.g., 1–4day activities) as delays without comparing them to an average baseline. - It mentions the “Implementação de Monitoração (ativação)” as delayed, though its duration is consistent (3–4 days) across projects. - Patterns across projects (e.g., repeated long durations in “Certificação da Implantação” or postimplementation followup) are not fully explored. Overall, it demonstrates partial understanding and reasonable reasoning but lacks depth and precision—hence a **2/3**. | F103: 2
A104: =_xlfn.CONCAT(C104,"_",D104) -> gpt-3.5-turbo_US37581_285851_293949_Q50 | B104: gpt-5-chat-latest | C104: gpt-3.5-turbo_US37581_285851_293949 | D104: Q50 | E104: **3** The answer accurately summarizes the deviations from the original plan across all three projects, correctly identifies specific lengthy tasks as indicators of delay, and provides a coherent overall conclusion that adherence was incomplete. It is concise, factually grounded in the event log, and aligns with the question’s focus on evaluating adherence to plan and objectives. | F104: =RIGHT(LEFT(E104,3),1) -> 3
A105: =_xlfn.CONCAT(C105,"_",D105) -> gpt-3.5-turbo_US37581_285851_293949_Q51 | B105: gpt-5-chat-latest | C105: gpt-3.5-turbo_US37581_285851_293949 | D105: Q51 | E105: **Grade: 3** The answer accurately identifies concrete examples of delays from the event log, connects them to plausible causes (technical complexity, coordination issues), and clearly explains how such obstacles would typically be managed (reassessment, reallocation, communication, escalation). The reasoning is coherent, grounded in evidence from the data, and complete in addressing both identification and management of issues—meeting the maximum quality criteria. | F105: 3
A106: =_xlfn.CONCAT(C106,"_",D106) -> gpt-3.5-turbo_US37581_285851_293949_Q52 | B106: gpt-5-chat-latest | C106: gpt-3.5-turbo_US37581_285851_293949 | D106: Q52 | E106: **2** The final conclusion recognizes the limitations of the available data and provides a balanced, reasonable summary that partially answers the question. It correctly notes that the event log alone isn’t enough to confirm whether the projects stayed within allocated resources, while offering relevant observations about task duration, collaboration, and potential inefficiencies. However, the answer stops short of a clear evaluative statement (e.g., even a tentative “it is unlikely” or “most likely yes”), which limits completeness and decisiveness — hence, a good but not top score. | F106: =RIGHT(LEFT(E106,3),1) -> 2
A107: =_xlfn.CONCAT(C107,"_",D107) -> gpt-3.5-turbo_US37581_285851_293949_Q53 | B107: gpt-5-chat-latest | C107: gpt-3.5-turbo_US37581_285851_293949 | D107: Q53 | E107: **3** The final conclusions correctly identify multiple relevant improvement areas—task duration analysis, resource allocation, and communication/coordination issues—all of which are supported by patterns observable in the event log. The recommendations are concrete, actionable, and directly tied to the causes of project delays. The reasoning is coherent and reflects a good understanding of project management improvement levers. | F107: =RIGHT(LEFT(E107,3),1) -> 3
A108: =_xlfn.CONCAT(C108,"_",D108) -> gpt-3.5-turbo_US37581_285851_293949_Q54 | B108: gpt-5-chat-latest | C108: gpt-3.5-turbo_US37581_285851_293949 | D108: Q54 | E108: **3** – The conclusion directly and correctly answers the question: it clearly states that not all milestones were achieved as planned and provides a concise, accurate justification (delays and extended task durations). The reasoning is consistent with the event log evidence and demonstrates understanding of the performance issues without unnecessary elaboration. | F108: =RIGHT(LEFT(E108,3),1) -> 3
A109: =_xlfn.CONCAT(C109,"_",D109) -> gpt-3.5-turbo_US37581_285851_293949_Q55 | B109: gpt-5-chat-latest | C109: gpt-3.5-turbo_US37581_285851_293949 | D109: Q55 | E109: **3** The final recommendations are clear, relevant, and directly connected to the issues implied by the event logs—delays, resource dependencies, and coordination inefficiencies. The answer provides a comprehensive and actionable set of suggestions (improving communication, refining planning, accelerating approvals, managing resources, regular monitoring, tool adoption, and training). It addresses both process and people aspects of project execution. Overall, it is wellaligned with the prompt’s objective—recommending improvements for future projects—and merits the maximum score. | F109: =RIGHT(LEFT(E109,3),1) -> 3
A110: =_xlfn.CONCAT(C110,"_",D110) -> gpt-3.5-turbo_US37581_285851_293949_Q56 | B110: gpt-5-chat-latest | C110: gpt-3.5-turbo_US37581_285851_293949 | D110: Q56 | E110: **3** The final conclusions are clear, relevant, and well-supported by evidence from the event logs. The answer correctly identifies key scope management lessons—such as the need to define scope early, maintain stakeholder alignment, and manage changes—and links them to concrete examples (e.g., delays caused by unclear scope and inter-team coordination issues). The reasoning stays aligned with the concept of project scope management and provides actionable insights. Overall, it fully addresses the prompt with accuracy and depth. | F110: =RIGHT(LEFT(E110,3),1) -> 3
A111: =_xlfn.CONCAT(C111,"_",D111) -> gpt-3.5-turbo_US37581_285851_293949_Q57 | B111: gpt-5-chat-latest | C111: gpt-3.5-turbo_US37581_285851_293949 | D111: Q57 | E111: **3** The final conclusions are clear, relevant, and well structured. They offer concrete, actionable advice directly aligned with the question prompt (“What advice would you give to future project teams based on this project’s experience?”). The recommendations—planning, communication, resource and risk management, progress monitoring, and learning from past projects—are all appropriate given the observed delays in the event logs. The answer is comprehensive, logically organized, and directly addresses lessons learned. | F111: =RIGHT(LEFT(E111,3),1) -> 3
A112: =_xlfn.CONCAT(C112,"_",D112) -> gpt-3.5-turbo_US37581_Q18 | B112: gpt-5-chat-latest | C112: gpt-3.5-turbo_US37581 | D112: Q18 | E112: **3** The answer correctly identifies that the event log allows one to assess timing but not budget performance. It notes that the project concluded on time according to the log and appropriately qualifies that the budget aspect cannot be evaluated with the provided data. The conclusion is accurate, complete, and appropriately cautious given the available information. | F112: =RIGHT(LEFT(E112,3),1) -> 3
A113: =_xlfn.CONCAT(C113,"_",D113) -> gpt-3.5-turbo_US37581_Q19 | B113: gpt-5-chat-latest | C113: gpt-3.5-turbo_US37581 | D113: Q19 | E113: **3** The final conclusions accurately identify that there were delays, pinpoint several specific tasks that took longer than expected, and provide plausible explanations (coordination issues, resource or approval delays, technical complexity). The answer connects observations from the event log to reasonable causes and synthesizes them into an overall interpretation. It is clear, consistent, and demonstrates a solid understanding of the question’s requirements — meriting the maximum score. | F113: =RIGHT(LEFT(E113,3),1) -> 3
A114: =_xlfn.CONCAT(C114,"_",D114) -> gpt-3.5-turbo_US37581_Q20 | B114: gpt-5-chat-latest | C114: gpt-3.5-turbo_US37581 | D114: Q20 | E114: **3** The final conclusion effectively answers the question. It clearly states that the project did not adhere well to the original plan and objectives, cites concrete examples of delays (e.g., “Montar DSOL…,” server setup tasks), and identifies scope creep (additional tasks not originally planned). The reasoning is accurate and directly supported by information from the event log. The answer is complete, coherent, and aligned with the evaluation prompt — thus it deserves the maximum score. | F114: =RIGHT(LEFT(E114,3),1) -> 3
A115: =_xlfn.CONCAT(C115,"_",D115) -> gpt-3.5-turbo_US37581_Q21 | B115: gpt-5-chat-latest | C115: gpt-3.5-turbo_US37581 | D115: Q21 | E115: **3** The final conclusions accurately identify specific tasks that deviated in duration, link those delays to plausible causes (complexity, technical or compliance issues), and explain reasonable management responses (collaboration, troubleshooting, coordination). The answer shows solid understanding of the event log data and addresses the question directly and coherently, with clear justification—meeting the criteria for the maximum score. | F115: =RIGHT(LEFT(E115,3),1) -> 3
A116: =_xlfn.CONCAT(C116,"_",D116) -> gpt-3.5-turbo_US37581_Q22 | B116: gpt-5-chat-latest | C116: gpt-3.5-turbo_US37581 | D116: Q22 | E116: **2** The conclusion is generally sound — it correctly notes that the event log alone doesn’t provide enough data to confirm adherence to resource constraints and suggests that some task durations might indicate inefficiencies. However, the answer remains somewhat generic and does not explicitly link the analysis to clear evidence of resource usage or deviations. It shows reasonable reasoning but lacks specificity and depth to warrant a top score. | F116: =RIGHT(LEFT(E116,3),1) -> 2
A117: =_xlfn.CONCAT(C117,"_",D117) -> gpt-3.5-turbo_US37581_Q23 | B117: gpt-5-chat-latest | C117: gpt-3.5-turbo_US37581 | D117: Q23 | E117: **3** The answer provides a clear, structured, and relevant set of improvement actions directly related to the project’s performance issues. It covers key project management domains—resource planning, communication, estimation, approval processes, issue resolution, and monitoring—each supported by specific examples tied to the event log. The suggestions are actionable and aligned with best practices, demonstrating solid understanding. Minor refinement in linking each recommendation more tightly to data evidence would make it even stronger, but overall, it fully meets the criteria for the highest grade. | F117: =RIGHT(LEFT(E117,3),1) -> 3
... A127: =_xlfn.CONCAT(C127,"_",D127) -> qwen3_US285851_Q33 | B127: gpt-5-chat-latest | C127: qwen3_US285851 | D127: Q33 | E127: **3** The final conclusions clearly identify the major sources of delay (e.g., 55day budget approval, duplicate and redundant tasks, prolonged postimplementation phase), link them to their likely causes, and propose realistic, actionable improvements such as streamlining approvals, consolidating duplicated work, managing dependencies, and enhancing communication and risk management. The reasoning is structured, specific, and demonstrates a solid understanding of project performance factors. | F127: =RIGHT(LEFT(E127,3),1) -> 3
A128: =_xlfn.CONCAT(C128,"_",D128) -> qwen3_US285851_Q34 | B128: gpt-5-chat-latest | C128: qwen3_US285851 | D128: Q34 | E128: **Grade: 3** **Explanation:** The final answer is clear, logically structured, and directly addresses the question. It correctly concludes that all milestones were achieved according to the event log, while also acknowledging possible delays and inefficiencies in specific tasks. The reasoning is evidence-based, refers to concrete examples (task IDs and durations), and provides a balanced conclusion distinguishing between technical completion and schedule performance. This reflects a comprehensive understanding of the data, justifying the maximum score. | F128: 3
A129: =_xlfn.CONCAT(C129,"_",D129) -> qwen3_US285851_Q35 | B129: gpt-5-chat-latest | C129: qwen3_US285851 | D129: Q35 | E129: **3** The final recommendations are well-reasoned, specific, and actionable. They correctly identify the main sources of delay (e.g., the 55day budget approval and 30day postimplementation phase), link them to potential root causes, and provide concrete improvement strategies such as streamlining approvals, standardizing documentation, clarifying task ownership, and enhancing communication. The advice is structured, comprehensive, and clearly tied to observed evidence in the event log, fully meeting the intent of the prompt. | F129: =RIGHT(LEFT(E129,3),1) -> 3
A130: =_xlfn.CONCAT(C130,"_",D130) -> qwen3_US285851_Q36 | B130: gpt-5-chat-latest | C130: qwen3_US285851 | D130: Q36 | E130: **3** The conclusions are well-structured, specific, and directly tied to evidence from the event log. The response identifies clear lessons about scope definition, redundancy, stakeholder alignment, and change control — all core aspects of scope management. It demonstrates understanding by linking observed delays (e.g., 55-day FOI approval, duplicated tasks, long post-implementation phase) to scope-related issues, and it provides actionable takeaways for future projects. Overall, it shows completeness, internal consistency, and relevance to the prompt. | F130: =RIGHT(LEFT(E130,3),1) -> 3
A131: =_xlfn.CONCAT(C131,"_",D131) -> qwen3_US285851_Q37 | B131: gpt-5-chat-latest | C131: qwen3_US285851 | D131: Q37 | E131: **3** – The final conclusions are wellstructured, directly address the main performance bottlenecks (budget approval, compliance, documentation, and postimplementation stages), and provide actionable, evidencebased advice for future teams. The recommendations are specific, relevant to the observed delays, and show clear understanding of project management improvement practices. | F131: =RIGHT(LEFT(E131,3),1) -> 3
A132: =_xlfn.CONCAT(C132,"_",D132) -> qwen3_US293949_Q38 | B132: gpt-5-chat-latest | C132: qwen3_US293949 | D132: Q38 | E132: **3** — The conclusion is clear, coherent, and accurately grounded in the evidence from the event log. It correctly explains that the deliverables appear completed on time (per the final recorded date) and explicitly notes that budget compliance cannot be assessed due to missing cost data. The reasoning is consistent and reflects an appropriate level of analysis based on the available information. | F132: =RIGHT(LEFT(E132,3),1) -> 3
A133: =_xlfn.CONCAT(C133,"_",D133) -> qwen3_US293949_Q39 | B133: gpt-5-chat-latest | C133: qwen3_US293949 | D133: Q39 | E133: **3** – The final conclusions are accurate, well organized, and comprehensive. They correctly identify the activities that took significantly longer—firewall configuration, deployment certification, and postimplementation followup—and reasonably explain them as likely delay points. The causes given (complex approvals, coordination among multiple teams, resource constraints, and compliance testing) are logically consistent with the event log. The answer goes beyond listing delays by grouping them thematically, discussing impact on the critical path, and offering practical recommendations. Overall, it demonstrates a complete and wellreasoned analysis worthy of the top score. | F133: =RIGHT(LEFT(E133,3),1) -> 3
A134: =_xlfn.CONCAT(C134,"_",D134) -> qwen3_US293949_Q40 | B134: gpt-5-chat-latest | C134: qwen3_US293949 | D134: Q40 | E134: **3** The concluding portion provides a clear and wellstructured evaluation directly addressing how well the project adhered to its plan and objectives. It identifies concrete evidence from the event log—specific tasks, durations, and patterns of delay—and logically connects these to causes such as rework, resource constraints, and planning gaps. The answer synthesizes observations into a coherent judgment (“did not adhere well”) and closes with practical lessons for improvement. Overall, it shows complete, accurate reasoning and alignment with the grading criteria. | F134: =RIGHT(LEFT(E134,3),1) -> 3
A135: =_xlfn.CONCAT(C135,"_",D135) -> qwen3_US293949_Q41 | B135: gpt-5-chat-latest | C135: qwen3_US293949 | D135: Q41 | E135: 3 The answer clearly identifies specific unexpected issues (long firewall, certification, and monitoring phases), links them to plausible causes (multi-team coordination, compliance work, and resource constraints), and reasonably explains how they were likely managed (phased execution, communication, and monitoring). It connects the analysis directly to the event log and provides a structured, evidencebased conclusion. | F135: 3
A136: =_xlfn.CONCAT(C136,"_",D136) -> qwen3_US293949_Q42 | B136: gpt-5-chat-latest | C136: qwen3_US293949 | D136: Q42 | E136: **2** The conclusion shows sound reasoning and references concrete evidence from the event log (tasks with unusually long durations and their assigned resources). It sensibly notes the absence of data on financial or technical resources and makes a plausible inference about human resource constraints. However, the assessment could be more concise, focused, and definitive—it wavers between acknowledging proper allocation and saying resources were insufficient. The reasoning is solid but not fully decisive or polished enough for the top score. | F136: =RIGHT(LEFT(E136,3),1) -> 2
A137: =_xlfn.CONCAT(C137,"_",D137) -> qwen3_US293949_Q43 | B137: gpt-5-chat-latest | C137: qwen3_US293949 | D137: Q43 | E137: **3** The conclusion is clear, specific, and well aligned with the event log data. It identifies concrete bottlenecks (firewall, certification, postimplementation monitoring), ties them to root causes (resource overload, sequential work), and proposes actionable improvements (parallelization, automation, better coordination, and standardization). The recommendations are relevant, detailed, and realistic within an IT infrastructure context. Overall, it demonstrates a solid understanding of project management and process optimization principles. | F137: =RIGHT(LEFT(E137,3),1) -> 3
A138: =_xlfn.CONCAT(C138,"_",D138) -> qwen3_US293949_Q44 | B138: gpt-5-chat-latest | C138: qwen3_US293949 | D138: Q44 | E138: **3** – The final conclusion correctly identifies that several milestones were not achieved as planned, clearly citing examples of delayed tasks and linking them to overall project schedule slippage. The reasoning is coherent, evidence-based, and directly answers the prompt. | F138: =RIGHT(LEFT(E138,3),1) -> 3
A139: =_xlfn.CONCAT(C139,"_",D139) -> qwen3_US293949_Q45 | B139: gpt-5-chat-latest | C139: qwen3_US293949 | D139: Q45 | E139: **3** The final recommendations are comprehensive, clearly structured, and well aligned with the issues identified in the event log. They address specific bottlenecks (like firewall rules and certification tasks), recognize resource allocation and coordination problems, propose process standardization, and include actionable mitigation steps such as automation, better communication, and contingency planning. The response connects observed delays to concrete recommendations and demonstrates awareness of project management best practices. Overall, it provides a strong, practical framework for improving future project execution. | F139: =RIGHT(LEFT(E139,3),1) -> 3
A140: =_xlfn.CONCAT(C140,"_",D140) -> qwen3_US293949_Q46 | B140: gpt-5-chat-latest | C140: qwen3_US293949 | D140: Q46 | E140: **3** The final conclusions demonstrate a strong grasp of scope management principles, clearly linking observed data (repeated tasks, long durations, coordination issues) to lessons learned. The answer identifies multiple, concrete causes—such as incomplete scope definition, scope creep, unclear documentation boundaries, and multiteam coordination gaps—and translates them into actionable scopemanagement lessons. It directly references evidence from the event log rather than remaining generic, making the reasoning both grounded and comprehensive. Overall, it meets the criteria for a toplevel (3) grading. | F140: =RIGHT(LEFT(E140,3),1) -> 3
A141: =_xlfn.CONCAT(C141,"_",D141) -> qwen3_US293949_Q47 | B141: gpt-5-chat-latest | C141: qwen3_US293949 | D141: Q47 | E141: **3** The final conclusions are comprehensive, clearly structured, and tightly linked to insights drawn from the event log. The advice addresses the main bottlenecks (multiteam coordination, certification, postimplementation phases, duplication of tasks, resource allocation, etc.) and provides specific, actionable recommendations—such as assigning ownership, standardizing workflows, and improving estimation methods. The analysis is both practical and relevant, reflecting a strong synthesis of patterns in the project data. | F141: =RIGHT(LEFT(E141,3),1) -> 3
...

Sheet GP5_judge3
A1: Master Key | B1: model | C1: projectID | D1: questionID | E1: answer | F1: Grade
A2: =_xlfn.CONCAT(C2,"_",D2) -> llama3.2_US285851_Q28 | B2: gpt-5-chat-latest | C2: llama3.2_US285851 | D2: Q28 | E2: **2** The final conclusion correctly identifies that there is insufficient information to conclusively determine whether the project was completed on time and within budget, while noting some apparent delays and inefficiencies in task execution. This shows partial understanding of the question and reasonable use of the data. However, the answer does not clearly connect the identified delays to actual project completion or budget outcomes, and some task examples appear somewhat arbitrary without a clear timing comparison or evidence of deviation from plan versus actual. Hence, it’s informative but lacks full analytical depth and clear conclusion—warranting a midrange score of **2/3**. | F2: =RIGHT(LEFT(E2,3),1) -> 2
A3: =_xlfn.CONCAT(C3,"_",D3) -> llama3.2_US285851_Q29 | B3: gpt-5-chat-latest | C3: llama3.2_US285851 | D3: Q29 | E3: **Grade: 2** **Justification:** The answer correctly identifies the main long-duration task (“Confirmar/garantir fonte orçamentária”) and notes repeated tasks such as “Atualizar o CMDB e gerar evidência” and “Cadastrar Servidor no GA – Windows,” which could indicate repeated effort or rework. It also provides reasonable hypotheses for causes (technical complexities, communication issues, project changes). However, the analysis contains minor inaccuracies—e.g., stating one “Cadastrar Servidor no GA – Windows” instance lasted 5 days when both lasted 3 days. It also misses other long-running tasks (e.g., “Acompanhar as atividades pós-implantação de infraestrutura” lasting 30 days) and does not clearly separate expected long tasks from abnormal delays. Overall, it shows sound reasoning and understanding of the dataset but lacks full accuracy and completeness—hence a **2/3**. | F3: 2
A4: =_xlfn.CONCAT(C4,"_",D4) -> llama3.2_US285851_Q30 | B4: gpt-5-chat-latest | C4: llama3.2_US285851 | D4: Q30 | E4: **2** The final conclusions demonstrate a solid understanding of the event log and identify major deviations (delays, repetition, and resource strain). The assessment addresses adherence to the plan in a reasonable way, though it remains somewhat generic and lacks explicit linkage to the original objectives or quantitative evaluation of adherence level. It’s coherent and accurate but not deeply analytical or comprehensive enough for the top score. | F4: =RIGHT(LEFT(E4,3),1) -> 2
A5: =_xlfn.CONCAT(C5,"_",D5) -> llama3.2_US285851_Q31 | B5: gpt-5-chat-latest | C5: llama3.2_US285851 | D5: Q31 | E5: **3** The final conclusions are coherent, specific, and clearly grounded in the event log data. The answer identifies concrete examples of potential issues (such as lengthy or repeated tasks), interprets their implications, and explains how they were managed. It also provides a balanced assessment, acknowledging delays while noting effective mitigation. The reasoning is complete, relevant, and aligns with the question prompt, justifying a top score. | F5: =RIGHT(LEFT(E5,3),1) -> 3
A6: =_xlfn.CONCAT(C6,"_",D6) -> llama3.2_US285851_Q32 | B6: gpt-5-chat-latest | C6: llama3.2_US285851 | D6: Q32 | E6: **2** The final conclusions are generally reasonable and aligned with the event log: they recognize delays and possible inefficiencies (notably the 55day task), while cautiously noting that there is insufficient data to confirm financial or staffing overruns. The answer does provide a balanced judgment that some tasks were likely resourceconstrained. However, it remains somewhat generic — it lacks a clear, evidencebased conclusion on whether the project stayed within the allocated resources, and it doesn’t connect specific log patterns quantitatively to that judgment. It’s thus above minimal quality (so not a 0 or 1) but not fully strong or conclusive enough for top marks. | F6: =RIGHT(LEFT(E6,3),1) -> 2
A7: =_xlfn.CONCAT(C7,"_",D7) -> llama3.2_US285851_Q33 | B7: gpt-5-chat-latest | C7: llama3.2_US285851 | D7: Q33 | E7: **3** The final conclusions are clear, structured, and well-aligned with the given event log. The answer identifies specific weaknesses (long durations, repetitive tasks, handover inefficiencies) and translates these into actionable recommendations (early risk identification, better handover procedures, improved testing and tracking). The reasoning is consistent with the evidence from the project log, and the improvement suggestions are realistic and relevant. Overall, it fully meets the criteria for a top score. | F7: =RIGHT(LEFT(E7,3),1) -> 3
A8: =_xlfn.CONCAT(C8,"_",D8) -> llama3.2_US285851_Q34 | B8: gpt-5-chat-latest | C8: llama3.2_US285851 | D8: Q34 | E8: **3** The final conclusion clearly answers the question (“No, not all project milestones were achieved as planned”) and supports that conclusion with relevant observations (duplicate tasks, zeroday tasks, overlapping or misstated durations, and timeline inconsistencies). The reasoning is coherent, and the conclusion matches the evidence. Minor inaccuracies or overinterpretations do not detract from the fact that it correctly and completely addresses the prompt. | F8: =RIGHT(LEFT(E8,3),1) -> 3
A9: =_xlfn.CONCAT(C9,"_",D9) -> llama3.2_US285851_Q35 | B9: gpt-5-chat-latest | C9: llama3.2_US285851 | D9: Q35 | E9: **3** — The final recommendations are clear, structured, and well aligned with the problem. They directly address causes of delay (resource allocation, task repetition, dependency management, long task durations, and monitoring). Each recommendation is actionable and reflects an understanding of typical project management and process improvement principles. The answer is coherent, relevant to the data provided, and demonstrates good synthesis of insights from the event log. | F9: =RIGHT(LEFT(E9,3),1) -> 3
A10: =_xlfn.CONCAT(C10,"_",D10) -> llama3.2_US285851_Q36 | B10: gpt-5-chat-latest | C10: llama3.2_US285851 | D10: Q36 | E10: **3** The final conclusions are wellstructured and directly address lessons learned about **project scope management**. The answer identifies concrete issues (such as inadequate planning, lack of task dependencies, inconsistent resource allocation, and unrealistic timelines) and links them to actionable lessons—improving planning, defining dependencies, and validating deliverables. It uses evidence from the event log (for example, Task5’s long duration) to justify its points. Overall, it provides a clear, relevant, and insightful synthesis without major omissions or inaccuracies, fully meeting the intent of the prompt. | F10: =RIGHT(LEFT(E10,3),1) -> 3
A11: =_xlfn.CONCAT(C11,"_",D11) -> llama3.2_US285851_Q37 | B11: gpt-5-chat-latest | C11: llama3.2_US285851 | D11: Q37 | E11: **3** The final conclusions are structured, relevant, and well-grounded in the event log data. They correctly identify key areas for improvement such as managing long-duration tasks, avoiding duplicated efforts, ensuring stakeholder communication, prioritizing based on business value, monitoring progress, and planning contingencies. The recommendations are actionable and show a solid understanding of the project performance issues. Overall, this is a strong, clear, and useful set of lessons learned deserving the maximum grade. | F11: =RIGHT(LEFT(E11,3),1) -> 3
A12: =_xlfn.CONCAT(C12,"_",D12) -> llama3.2_US293949_Q38 | B12: gpt-5-chat-latest | C12: llama3.2_US293949 | D12: Q38 | E12: **2** The conclusion correctly identifies that the project deliverables were *not all completed on time* and that determining *budget performance* is not possible with the given data. It also references evidence from the event log (e.g., tasks continuing after closure, variation in durations), showing some engagement with the dataset. However, the response contains a factual inaccuracy — the project closure is actually on **18–20.09.2024** (Tasks 68–69), not **16.09.2024** — and it partially misinterprets normal postclosure administrative tasks as signs of project delay. The explanation about budget is reasonable but not supported by explicit data analysis. Overall, the answer shows partial understanding and moderate accuracy, meriting a **2 (adequate but not strong)**. | F12: =RIGHT(LEFT(E12,3),1) -> 2
A13: =_xlfn.CONCAT(C13,"_",D13) -> llama3.2_US293949_Q39 | B13: gpt-5-chat-latest | C13: llama3.2_US293949 | D13: Q39 | E13: **3** The final conclusions are coherent, complete, and wellaligned with the prompt. The answer correctly identifies tasks whose durations deviate from the 1 to 2day norm, names plausible causes (security processes, configuration approvals, compliance checks), and provides constructive recommendations (dependency review, communication, tracking). The analysis covers both observation and mitigation aspects, making it fully correct and thorough. | F13: =RIGHT(LEFT(E13,3),1) -> 3
A14: =_xlfn.CONCAT(C14,"_",D14) -> llama3.2_US293949_Q40 | B14: gpt-5-chat-latest | C14: llama3.2_US293949 | D14: Q40 | E14: **2** The conclusion is generally correct in identifying that the project mostly adhered to the plan but faced delays in some phases (notably firewall configuration and certification). It provides a reasonable summary and points to key bottlenecks. However, the quantitative analysis in the final section seems somewhat arbitrary (percentages not clearly derived from data), and it doesn’t deeply connect delays to overall objectives or critical path performance. The reasoning is coherent but lacks depth and evidence-based precision, preventing a top score. | F14: =RIGHT(LEFT(E14,3),1) -> 2
A15: =_xlfn.CONCAT(C15,"_",D15) -> llama3.2_US293949_Q41 | B15: gpt-5-chat-latest | C15: llama3.2_US293949 | D15: Q41 | E15: **3** The final conclusions clearly identify specific delayed tasks (e.g., firewall rules, server registration, monitoring) and logically infer the types of obstacles (security configuration, provisioning, installation issues). It also proposes concrete, relevant management strategies (root cause analysis, stakeholder communication, resource reallocation, contingency planning). The answer demonstrates sound reasoning and good alignment with the question on unexpected issues and their management. | F15: =RIGHT(LEFT(E15,3),1) -> 3
... A28: =_xlfn.CONCAT(C28,"_",D28) -> llama3.2_US37581_285851_293949_Q54 | B28: gpt-5-chat-latest | C28: llama3.2_US37581_285851_293949 | D28: Q54 | E28: **1** The conclusion is vague and does not clearly answer the core question: *“Were all project milestones achieved as planned?”* The response repeats observations about timing inconsistencies but fails to give a definitive statement on milestone completion or alignment with plans. It also incorrectly assumes a missing project when all three were provided, which shows incomplete understanding. Overall, it demonstrates partial analysis effort but lacks a clear, evidencebased judgment, so it deserves a lowtomid grade of **1/3**. | F28: =RIGHT(LEFT(E28,3),1) -> 1
A29: =_xlfn.CONCAT(C29,"_",D29) -> llama3.2_US37581_285851_293949_Q55 | B29: gpt-5-chat-latest | C29: llama3.2_US37581_285851_293949 | D29: Q55 | E29: **Grade: 2** **Rationale:** The final recommendations are generally sound and follow standard project management best practices — clear scope, critical path identification, scheduling, risk management, resource planning, and lessons learned. These are all valid and applicable suggestions. However, the answer is somewhat generic and does not specifically tie the recommendations to the *actual patterns or delays observed* in the provided event logs (e.g., long durations in "Confirmar fonte orçamentária" or "Certificação da Implantação" steps). It misses an opportunity to contextualize its advice with data-driven insights from the case. Thus, while complete and coherent at a general level, it lacks evidence of project log analysis and specific linkage to observed bottlenecks — justifying a solid but not top grade (2 out of 3). | F29: 2
A30: =_xlfn.CONCAT(C30,"_",D30) -> llama3.2_US37581_285851_293949_Q56 | B30: gpt-5-chat-latest | C30: llama3.2_US37581_285851_293949 | D30: Q56 | E30: **2** The answer demonstrates a reasonable understanding of project scope management and provides plausible inferred lessons (clarifying requirements, managing scope creep, aligning stakeholders). It also attempts to connect these to specific tasks from the logs, showing some contextual effort. However, the connections to the actual event data are weak and somewhat speculative, lacking concrete evidence or clear linkage to the provided logs. The overall conclusion is generic rather than deeply analytical. Thus, it merits a **2** for being partially relevant and reasonably complete, but not fully grounded or strongly supported. | F30: =RIGHT(LEFT(E30,3),1) -> 2
A31: =_xlfn.CONCAT(C31,"_",D31) -> llama3.2_US37581_285851_293949_Q57 | B31: gpt-5-chat-latest | C31: llama3.2_US37581_285851_293949 | D31: Q57 | E31: **3** The concluding part of the answer is comprehensive, clear, and wellstructured. It provides actionable, relevant, and logically organized advice that clearly stems from generic project management lessons applicable to the kind of delays and dependencies seen in the provided event logs. It covers key domains—communication, risk management, resource allocation, quality assurance, stakeholder engagement, and postproject review—showing a mature synthesis of learning. While it does not tie every recommendation explicitly to the details of the specific event log, its breadth, coherence, and practical usefulness justify the maximum grade. | F31: =RIGHT(LEFT(E31,3),1) -> 3
A32: =_xlfn.CONCAT(C32,"_",D32) -> llama3.2_US37581_Q18 | B32: gpt-5-chat-latest | C32: llama3.2_US37581 | D32: Q18 | E32: **2** The conclusion provides a reasonable evaluation that the project was *generally* completed on time and within budget, while also identifying and discussing specific delayed tasks. It shows awareness of schedule performance by referencing concrete examples from the event log. However, the answer lacks clear evidence or quantitative assessment linking the delays directly to overall project timing or budget overruns. The statement about "repeated tasks" is somewhat inaccurate (Tasks 54 and 64 are not the same), which slightly weakens the accuracy. Overall, a good but not fully precise answer — hence a score of **2/3**. | F32: =RIGHT(LEFT(E32,3),1) -> 2
A33: =_xlfn.CONCAT(C33,"_",D33) -> llama3.2_US37581_Q19 | B33: gpt-5-chat-latest | C33: llama3.2_US37581 | D33: Q19 | E33: **Grade: 3** The final conclusions of the answer show a solid understanding of the event log and provide a coherent analysis of where and why delays occurred. The response identifies specific timeframes and tasks affected, ties them to plausible causes such as task complexity, resource constraints, and project management inefficiencies, and offers realistic mitigation strategies. The reasoning is structured, accurate, and supported by evidence from the log. Minor inaccuracies in interpreting durations do not significantly detract from the overall quality, making this a well-reasoned, high-quality answer deserving of the maximum score. | F33: 3
A34: =_xlfn.CONCAT(C34,"_",D34) -> llama3.2_US37581_Q20 | B34: gpt-5-chat-latest | C34: llama3.2_US37581 | D34: Q20 | E34: **2** The conclusion provides a balanced and partially substantiated assessment. It recognizes both the project’s adherence (tasks largely completed, adaptability, collaboration) and its shortcomings (delays, communication issues, possible scope creep). However, the analysis remains somewhat generic — it doesn’t strongly connect observations to the actual impact on the project’s original objectives or schedule adherence. The reasoning is sound but lacks depth and precision, fitting a **“good but incomplete”** evaluation rather than an excellent or minimal one. | F34: =RIGHT(LEFT(E34,3),1) -> 2
A35: =_xlfn.CONCAT(C35,"_",D35) -> llama3.2_US37581_Q21 | B35: gpt-5-chat-latest | C35: llama3.2_US37581 | D35: Q21 | E35: **3** The final conclusions effectively identify specific tasks that experienced unexpected delays, provide plausible reasons for these issues (e.g., technical complexity, inter-team dependencies), and clearly explain how such obstacles were managed (e.g., reallocating resources, communicating with stakeholders, adjusting timelines). The answer is coherent, well-grounded in the event log, and demonstrates a solid understanding of project management response strategies. | F35: =RIGHT(LEFT(E35,3),1) -> 3
A36: =_xlfn.CONCAT(C36,"_",D36) -> llama3.2_US37581_Q22 | B36: gpt-5-chat-latest | C36: llama3.2_US37581 | D36: Q22 | E36: **2** **Justification:** The final conclusions in the provided answer show a reasonable understanding of resource management issues, such as over-allocation and uneven distribution of effort among teams. The reasoning is coherent and tied to specific tasks (e.g., Task 27, Tasks 30–31). However, the analysis lacks direct evidence that the project exceeded financial or technical resources, which was explicitly part of the question (“human, financial, technical”). The claims about over-allocation are somewhat speculative and not strongly supported by quantitative evidence from the log. Overall, the answer identifies relevant patterns and provides useful recommendations but falls short of a comprehensive and well-substantiated evaluation. Hence, it deserves a **2 (good but incomplete)** on a 0–3 scale. | F36: =RIGHT(LEFT(E36,3),1) -> 2
A37: =_xlfn.CONCAT(C37,"_",D37) -> llama3.2_US37581_Q23 | B37: gpt-5-chat-latest | C37: llama3.2_US37581 | D37: Q23 | E37: **3** The final conclusions are comprehensive, coherent, and well aligned with the question. The answer identifies concrete causes of delay (long-duration and complex tasks, dependencies, lack of parallelization) and then proposes specific, actionable improvements (task decomposition, better scheduling, agile methodology, continuous monitoring). The reasoning connects observations from the event log to the recommendations in a logical way, showing understanding of both project management and process improvement principles. It directly addresses “what could have been done differently” and presents a realistic improvement strategy — deserving the maximum score. | F37: =RIGHT(LEFT(E37,3),1) -> 3
A38: =_xlfn.CONCAT(C38,"_",D38) -> llama3.2_US37581_Q24 | B38: gpt-5-chat-latest | C38: llama3.2_US37581 | D38: Q24 | E38: **2** — The final conclusion appropriately states that there were deviations from the planned timeline and that not all milestones appear to have been achieved exactly as planned. It references specific examples of delayed or repeated tasks and reasonably cautions that the overall project success cannot be fully assessed without further details. However, the answer includes some assumptions about “expected completion dates” not supported by the event log and could be clearer and more concise in summarizing whether milestones were met overall. The reasoning shows good understanding but lacks precise evidence or reference to official milestones. | F38: =RIGHT(LEFT(E38,3),1) -> 2
A39: =_xlfn.CONCAT(C39,"_",D39) -> llama3.2_US37581_Q25 | B39: gpt-5-chat-latest | C39: llama3.2_US37581 | D39: Q25 | E39: **3** The concluding recommendations are clear, actionable, and directly derived from an analysis of the event log. They identify relevant improvement areas—task decomposition, resource allocation, dependency management, and monitoring/reporting—which align well with common project management best practices. The answer moves logically from observed patterns to practical, forward-looking suggestions, demonstrating good synthesis and relevance. | F39: =RIGHT(LEFT(E39,3),1) -> 3
A40: =_xlfn.CONCAT(C40,"_",D40) -> llama3.2_US37581_Q26 | B40: gpt-5-chat-latest | C40: llama3.2_US37581 | D40: Q26 | E40: **3** The final conclusions are accurate, clear, and well-structured. They identify relevant lessons learned that demonstrate understanding of project scope management: unclear dependencies, lack of parallelization, resource constraints, insufficient monitoring, and evidence of scope creep. The improvement suggestions directly align with standard scope management best practices (defining dependencies, controlling scope, allocating resources). The reasoning logically connects observations from the event log to lessons learned, showing depth and coherence. Overall, this deserves the maximum grade on the 0–3 scale. | F40: =RIGHT(LEFT(E40,3),1) -> 3
A41: =_xlfn.CONCAT(C41,"_",D41) -> llama3.2_US37581_Q27 | B41: gpt-5-chat-latest | C41: llama3.2_US37581 | D41: Q27 | E41: **3** The conclusions are clear, specific, and well-grounded in the event log evidence. The answer provides actionable and relevant advice aligned with the data—highlighting bottlenecks, dependencies, resource utilization, contingency planning, communication, and postimplementation followup. Each recommendation connects logically to observed project behavior, demonstrating good analytical understanding. Minor verbosity aside, the final part effectively synthesizes lessons learned for future teams. | F41: =RIGHT(LEFT(E41,3),1) -> 3
A42: =_xlfn.CONCAT(C42,"_",D42) -> gpt-4o_US285851_Q28 | B42: gpt-5-chat-latest | C42: gpt-4o_US285851 | D42: Q28 | E42: **3** The answer clearly and accurately evaluates project timeliness and budget adherence given the available data. It identifies major delays supported by specific tasks and durations, acknowledges the lack of direct budget data, and logically infers possible impacts on cost. The conclusion is coherent and wellreasoned: some deliverables were delayed, and while the project was completed, it probably exceeded planned timelines and may have faced budget constraints. Overall, the final conclusion is complete, evidencebased, and consistent with the provided event log. | F42: =RIGHT(LEFT(E42,3),1) -> 3
A43: =_xlfn.CONCAT(C43,"_",D43) -> gpt-4o_US285851_Q29 | B43: gpt-5-chat-latest | C43: gpt-4o_US285851 | D43: Q29 | E43: **3** The answer correctly identifies the main source of delays — the budget approval task — and supports it with quantitative details from the event log. It also recognizes secondary contributors such as cross-team coordination issues, overlapping tasks managed by the same resource, and time-consuming certification steps. The reasoning is consistent with the data and the conclusions are clearly structured and well supported. Overall, it fully addresses the prompt and provides a strong explanation of the causes behind the delays. | F43: =RIGHT(LEFT(E43,3),1) -> 3
A44: =_xlfn.CONCAT(C44,"_",D44) -> gpt-4o_US285851_Q30 | B44: gpt-5-chat-latest | C44: gpt-4o_US285851 | D44: Q30 | E44: **3** – The conclusion demonstrates a clear, wellreasoned evaluation aligned with the prompt. It summarizes delays, identifies the key bottleneck (budget confirmation), discusses resource and timeline consistency, and concludes that the project largely adhered to plan and objectives despite minor deviations. The response is coherent, evidencebased, and appropriately balanced, earning the maximum score. | F44: =RIGHT(LEFT(E44,3),1) -> 3
A45: =_xlfn.CONCAT(C45,"_",D45) -> gpt-4o_US285851_Q31 | B45: gpt-5-chat-latest | C45: gpt-4o_US285851 | D45: Q31 | E45: **3** The final conclusions accurately identify the main unexpected issues (the unusually long budget confirmation and postimplementation monitoring) and provide reasonable explanations and management responses (stakeholder communication, extended monitoring for stability). The reasoning is coherent, specific, and tied to the event log data, satisfying the question’s requirements completely. | F45: =RIGHT(LEFT(E45,3),1) -> 3
... A97: =_xlfn.CONCAT(C97,"_",D97) -> gpt-3.5-turbo_US293949_Q43 | B97: gpt-5-chat-latest | C97: gpt-3.5-turbo_US293949 | D97: Q43 | E97: **3** The final conclusions are clear, structured, and aligned with best project management practices. They identify specific improvement areas — task prioritization, resource allocation, detailed planning, monitoring, communication, training, and risk management — all directly relevant to improving project efficiency and reducing delays. The recommendations are actionable and realistic given the context of an IT infrastructure implementation. Overall, the answer demonstrates a solid understanding of project improvement strategies and deserves the maximum grade. | F97: =RIGHT(LEFT(E97,3),1) -> 3
A98: =_xlfn.CONCAT(C98,"_",D98) -> gpt-3.5-turbo_US293949_Q44 | B98: gpt-5-chat-latest | C98: gpt-3.5-turbo_US293949 | D98: Q44 | E98: **Grade: 2** **Reasoning:** The answer correctly identifies that not all project milestones were achieved as planned, and it briefly mentions that some tasks took longer than expected, indicating delays. However, it lacks specific examples or details to substantiate the claim (e.g., referencing which milestones or phases experienced delays such as firewall release, certification, or monitoring). It gives a generally correct but superficial conclusion—accurate in direction but not fully developed. | F98: 2
A99: =_xlfn.CONCAT(C99,"_",D99) -> gpt-3.5-turbo_US293949_Q45 | B99: gpt-5-chat-latest | C99: gpt-3.5-turbo_US293949 | D99: Q45 | E99: **3** The final recommendations are clear, relevant, and directly address the main issues inferred from the event log, such as scheduling accuracy, coordination among teams, and risk monitoring. The points are structured, actionable, and show a good understanding of project management best practices (e.g., post-project analysis, checkpoints, continuous monitoring). The answer is complete and aligned with the problem context, with no major omissions or inaccuracies. | F99: =RIGHT(LEFT(E99,3),1) -> 3
A100: =_xlfn.CONCAT(C100,"_",D100) -> gpt-3.5-turbo_US293949_Q46 | B100: gpt-5-chat-latest | C100: gpt-3.5-turbo_US293949 | D100: Q46 | E100: **3** The final conclusions effectively address project scope management lessons drawn from the event log. The answer identifies key issues—poor task definition, inaccurate time estimation, and potential scope creep—and ties them to concrete examples from the project. It also provides actionable recommendations for better scope control (clearer task definition, accurate estimation, regular monitoring, and scope reviews). The reasoning is relevant, consistent with project management principles, and grounded in the provided data. | F100: =RIGHT(LEFT(E100,3),1) -> 3
A101: =_xlfn.CONCAT(C101,"_",D101) -> gpt-3.5-turbo_US293949_Q47 | B101: gpt-5-chat-latest | C101: gpt-3.5-turbo_US293949 | D101: Q47 | E101: **3** The final conclusions are clear, structured, and relevant to the given project scenario. The advice covers key areas affecting project performance — communication, critical path identification, resource allocation, dependency management, adaptive planning, and lessons learned. Each recommendation logically connects to issues reflected in the event log (e.g., multi-day delays, resource overlaps, and extended certification periods). The response shows comprehensive understanding and provides actionable guidance, warranting the maximum score. | F101: =RIGHT(LEFT(E101,3),1) -> 3
A102: =_xlfn.CONCAT(C102,"_",D102) -> gpt-3.5-turbo_US37581_285851_293949_Q48 | B102: gpt-5-chat-latest | C102: gpt-3.5-turbo_US37581_285851_293949 | D102: Q48 | E102: **3** – The conclusion accurately recognizes that, based on the event log alone, there is insufficient information to determine whether projects were completed on time and within budget. It correctly identifies the missing data (original timelines, milestones, and budgets) and highlights the need for comparison with baseline plans. The reasoning is accurate, complete, and clearly aligned with the question. | F102: =RIGHT(LEFT(E102,3),1) -> 3
A103: =_xlfn.CONCAT(C103,"_",D103) -> gpt-3.5-turbo_US37581_285851_293949_Q49 | B103: gpt-5-chat-latest | C103: gpt-3.5-turbo_US37581_285851_293949 | D103: Q49 | E103: **3** The final answer identifies specific delayed tasks with concrete evidence from the event log (durations longer than usual), correctly associates them with the relevant project (US37581), and provides plausible underlying causes such as resource constraints or technical and coordination challenges. It demonstrates strong understanding, precision, and alignment with the prompt’s request to pinpoint performance issues and their potential causes. | F103: =RIGHT(LEFT(E103,3),1) -> 3
A104: =_xlfn.CONCAT(C104,"_",D104) -> gpt-3.5-turbo_US37581_285851_293949_Q50 | B104: gpt-5-chat-latest | C104: gpt-3.5-turbo_US37581_285851_293949 | D104: Q50 | E104: **2** The answer correctly identifies that deviations occurred across the three projects and cites specific tasks as examples of delays. It also delivers a reasonable overall conclusion that the projects faced challenges adhering to the original plan and objectives. However, the evaluation remains somewhat superficial: - It lacks quantitative or comparative analysis (e.g., how much total delay occurred, whether deviations were significant in context). - Some examples are observational but not well justified as deviations from the original *planned* durations (since baseline plan data isn’t explicitly given). - The conclusion is general and doesn’t differentiate the degree of adherence among projects. Thus, while the reasoning is directionally correct and grounded in the logs, the depth and precision are moderate—consistent with a **grade of 2 (good but not thorough)**. | F104: =RIGHT(LEFT(E104,3),1) -> 2
A105: =_xlfn.CONCAT(C105,"_",D105) -> gpt-3.5-turbo_US37581_285851_293949_Q51 | B105: gpt-5-chat-latest | C105: gpt-3.5-turbo_US37581_285851_293949 | D105: Q51 | E105: **3** The conclusion accurately identifies projectspecific delays from the event logs and links them to likely unexpected issues. It notes examples across all three projects and clearly explains potential management responses (reassessment, resource reallocation, communication, timeline adjustments). The explanation is coherent, relevant, and complete, fully addressing both “what issues” and “how they were managed.” | F105: =RIGHT(LEFT(E105,3),1) -> 3
A106: =_xlfn.CONCAT(C106,"_",D106) -> gpt-3.5-turbo_US37581_285851_293949_Q52 | B106: gpt-5-chat-latest | C106: gpt-3.5-turbo_US37581_285851_293949 | D106: Q52 | E106: **Grade: 3** **Justification:** The conclusion accurately summarizes the evidence from the event log and gives a logically consistent, wellgrounded answer to the question about resource management. It identifies delays and overlapping resource assignments, explains how these indicate challenges in staying within the allocated human and technical resources, and appropriately notes that financial data is not directly discernible from the log but could be indirectly affected. The reasoning is coherent, balanced, and draws reasonable inferences given the data. | F106: 3
A107: =_xlfn.CONCAT(C107,"_",D107) -> gpt-3.5-turbo_US37581_285851_293949_Q53 | B107: gpt-5-chat-latest | C107: gpt-3.5-turbo_US37581_285851_293949 | D107: Q53 | E107: **3** The final conclusions are well organized, directly address the question, and align with the issues observable in the event log (e.g., approval bottlenecks, resource allocation delays, dependency management). The answer presents clear, actionable recommendations—streamlining approvals, improving resource planning, enhancing communication, and leveraging technology—all of which are relevant and practical improvements for project performance. Overall, it demonstrates solid understanding and provides comprehensive, meaningful insights deserving of the maximum score. | F107: =RIGHT(LEFT(E107,3),1) -> 3
A108: =_xlfn.CONCAT(C108,"_",D108) -> gpt-3.5-turbo_US37581_285851_293949_Q54 | B108: gpt-5-chat-latest | C108: gpt-3.5-turbo_US37581_285851_293949 | D108: Q54 | E108: **3** The conclusion accurately answers the question about whether milestones were achieved as planned. It directly states that not all milestones were met and supports the conclusion with concrete examples from each of the three project IDs. The reasoning is clear, relevant, and consistent with the data provided in the event log. | F108: =RIGHT(LEFT(E108,3),1) -> 3
A109: =_xlfn.CONCAT(C109,"_",D109) -> gpt-3.5-turbo_US37581_285851_293949_Q55 | B109: gpt-5-chat-latest | C109: gpt-3.5-turbo_US37581_285851_293949 | D109: Q55 | E109: **3** The final recommendations are clear, relevant, and directly address the causes of delay identified in the event log. They cover key improvement areas such as resource allocation, approval flows, communication, monitoring, and task duration optimization — all of which are supported by the data. The answer is structured, actionable, and demonstrates an understanding of project management improvement practices. | F109: =RIGHT(LEFT(E109,3),1) -> 3
A110: =_xlfn.CONCAT(C110,"_",D110) -> gpt-3.5-turbo_US37581_285851_293949_Q56 | B110: gpt-5-chat-latest | C110: gpt-3.5-turbo_US37581_285851_293949 | D110: Q56 | E110: **3** The final conclusions are well-structured, relevant, and demonstrate a solid understanding of project scope management. The answer identifies key lessons—such as the importance of clear scope definition, detailed planning, stakeholder communication, change control, and risk management—which are directly aligned with best practices. Although somewhat general, the conclusions are coherent, accurate, and comprehensive given the available event log context. | F110: =RIGHT(LEFT(E110,3),1) -> 3
A111: =_xlfn.CONCAT(C111,"_",D111) -> gpt-3.5-turbo_US37581_285851_293949_Q57 | B111: gpt-5-chat-latest | C111: gpt-3.5-turbo_US37581_285851_293949 | D111: Q57 | E111: **3** The answer provides comprehensive, relevant, and wellstructured advice that directly aligns with lessons observable from the project logs—planning, communication, risk mitigation, resource allocation, monitoring delays, and continuous improvement. The recommendations are clear, actionable, and encompass both procedural and managerial aspects, making it a complete and highquality conclusion. | F111: =RIGHT(LEFT(E111,3),1) -> 3
A112: =_xlfn.CONCAT(C112,"_",D112) -> gpt-3.5-turbo_US37581_Q18 | B112: gpt-5-chat-latest | C112: gpt-3.5-turbo_US37581 | D112: Q18 | E112: **3** The conclusion accurately addresses both components of the question based on the evidence available. It correctly identifies that the event log shows the project was completed on time and appropriately notes that there is insufficient information to assess the budget. The reasoning is clear, factual, and complete given the provided data. | F112: =RIGHT(LEFT(E112,3),1) -> 3
A113: =_xlfn.CONCAT(C113,"_",D113) -> gpt-3.5-turbo_US37581_Q19 | B113: gpt-5-chat-latest | C113: gpt-3.5-turbo_US37581 | D113: Q19 | E113: **3** The answer accurately identifies multiple tasks with unusually long durations, links them to plausible causes (e.g., complex checklists, approval delays, multi-team coordination), and provides a coherent overall explanation of the likely delay factors. The reasoning aligns with the data in the event log and shows clear understanding of project dynamics. It is complete, specific, and wellsupported—consistent with a topscore (3) evaluation. | F113: =RIGHT(LEFT(E113,3),1) -> 3
A114: =_xlfn.CONCAT(C114,"_",D114) -> gpt-3.5-turbo_US37581_Q20 | B114: gpt-5-chat-latest | C114: gpt-3.5-turbo_US37581 | D114: Q20 | E114: **3** The conclusion is accurate and well-supported by the event log. It clearly identifies that the project did not adhere well to the original plan and objectives, citing specific examples of delayed and added tasks and connecting these issues to possible causes such as poor estimation, resource management, and scope definition. The reasoning aligns with the data presented and summarizes the performance appropriately. | F114: =RIGHT(LEFT(E114,3),1) -> 3
A115: =_xlfn.CONCAT(C115,"_",D115) -> gpt-3.5-turbo_US37581_Q21 | B115: gpt-5-chat-latest | C115: gpt-3.5-turbo_US37581 | D115: Q21 | E115: **3** The final portion of the answer directly identifies several unexpected issues backed by evidence from the event log (e.g., delayed tasks, multi-resource coordination, and technical configuration challenges). It also reasonably explains how these issues were managed—through communication, escalation, timeline adjustments, and resource reallocation. The response demonstrates good understanding of the project log, clearly outlines both causes and management strategies, and stays relevant to the prompt. It is complete and well justified, deserving the maximum score. | F115: =RIGHT(LEFT(E115,3),1) -> 3
A116: =_xlfn.CONCAT(C116,"_",D116) -> gpt-3.5-turbo_US37581_Q22 | B116: gpt-5-chat-latest | C116: gpt-3.5-turbo_US37581 | D116: Q22 | E116: **2** The answer is generally coherent, demonstrates understanding of the question, and references relevant details from the event log (e.g., key roles, project duration, long task durations). It correctly concludes that with the given data it’s not possible to confirm whether the project stayed within allocated resources, while pointing out possible indications of resource challenges. However, the conclusion remains somewhat generic — it restates uncertainty without tying it explicitly to measurable resource indicators (human availability, cost overruns, technical capacity). More specific linkage between observed delays and probable resource overuse would have strengthened the argument. | F116: =RIGHT(LEFT(E116,3),1) -> 2
A117: =_xlfn.CONCAT(C117,"_",D117) -> gpt-3.5-turbo_US37581_Q23 | B117: gpt-5-chat-latest | C117: gpt-3.5-turbo_US37581 | D117: Q23 | E117: **3** The conclusion is clear, relevant, and demonstrates a solid understanding of project management improvement strategies. It addresses multiple key areas—dependency management, resource allocation, communication, risk management, progress monitoring, and process optimization—all directly applicable to the provided event log and likely root causes of delays. The recommendations are actionable, comprehensive, and show coherence with the context of an IT infrastructure implementation project. Overall, this is a complete and wellreasoned final answer deserving the maximum grade. | F117: =RIGHT(LEFT(E117,3),1) -> 3
A118: =_xlfn.CONCAT(C118,"_",D118) -> gpt-3.5-turbo_US37581_Q24 | B118: gpt-5-chat-latest | C118: gpt-3.5-turbo_US37581 | D118: Q24 | E118: **2** The final answer correctly identifies that not all milestones were achieved as planned and provides examples of tasks that took longer than expected. It shows good understanding of the project schedule and relates delays to performance issues. However, the justification has minor inaccuracies (for instance, it assumes a deviation from a “planned” duration without explicit reference to a baseline plan) and does not provide a complete project-level assessment. Therefore, it deserves above-average but not top marks. | F118: =RIGHT(LEFT(E118,3),1) -> 2
... A151: =_xlfn.CONCAT(C151,"_",D151) -> qwen3_US37581_285851_293949_Q57 | B151: gpt-5-chat-latest | C151: qwen3_US37581_285851_293949 | D151: Q57 | E151: **3** The final advice section is detailed, structured, and fully aligned with the project data. It identifies key inefficiencies (task duplication, unclear roles, redundant monitoring periods, overlapping schedules) and translates them into actionable recommendations. The reasoning is rooted in evidence from the event log and covers both process and resource management improvements. The answer demonstrates a comprehensive understanding of the project dynamics and offers practical, relevant guidance for future teams. | F151: =RIGHT(LEFT(E151,3),1) -> 3
A152: =_xlfn.CONCAT(C152,"_",D152) -> qwen3_US37581_Q18 | B152: gpt-5-chat-latest | C152: qwen3_US37581 | D152: Q18 | E152: **Grade: 3** The conclusion is clear, coherent, and well reasoned given the available data. It correctly identifies that the event log lacks explicit baseline or budget information, so claims about timeliness or cost compliance must remain qualified. It highlights longduration tasks that could indicate bottlenecks, and it provides a balanced, evidencebased assessment: likely completed on time assuming the closure date matches the planned end, but impossible to evaluate budget adherence. Overall, the final portion accurately answers the prompt, respects the limits of the provided information, and justifies its conclusions — deserving the maximum score. | F152: 3
A153: =_xlfn.CONCAT(C153,"_",D153) -> qwen3_US37581_Q19 | B153: gpt-5-chat-latest | C153: qwen3_US37581 | D153: Q19 | E153: **3** The final answer accurately identifies concrete tasks with abnormally long durations, links them plausibly to probable causes (certification procedures, postimplementation followups, technical/configuration complexity, and resource constraints), and summarizes delay factors clearly. It is internally consistent, interprets the event log well, and provides a balanced conclusion. | F153: =RIGHT(LEFT(E153,3),1) -> 3
A154: =_xlfn.CONCAT(C154,"_",D154) -> qwen3_US37581_Q20 | B154: gpt-5-chat-latest | C154: qwen3_US37581 | D154: Q20 | E154: **3** — The answer clearly identifies several concrete indicators of poor adherence (e.g., longduration and repeated tasks, dependency delays, timeline extension) and ties them explicitly to the question about plan and objectives. It organizes evidence logically, distinguishes causes (client input, rework, underestimated effort) from results (schedule overrun, inefficiency), and concludes with a balanced judgment and recommendations. Overall, it’s a complete, wellreasoned assessment deserving the top grade. | F154: =RIGHT(LEFT(E154,3),1) -> 3
A155: =_xlfn.CONCAT(C155,"_",D155) -> qwen3_US37581_Q21 | B155: gpt-5-chat-latest | C155: qwen3_US37581 | D155: Q21 | E155: **3** The concluding answer is coherent, datadriven, and clearly connects specific longduration tasks in the event log to plausible unexpected issues. It then explains how each was managed (through extended timelines, crossteam collaboration, and iterative approvals). The reasoning is consistent with the provided evidence and offers concrete, realistic management responses. It meets the expected standard for accuracy, completeness, and clarity. | F155: =RIGHT(LEFT(E155,3),1) -> 3
A156: =_xlfn.CONCAT(C156,"_",D156) -> qwen3_US37581_Q22 | B156: gpt-5-chat-latest | C156: qwen3_US37581 | D156: Q22 | E156: **3** The conclusion is clear, logically structured, and directly addresses the question. It accurately interprets the task durations and resource overlaps as indicators that the project likely exceeded its allocated human and technical resources. The justification is detailed yet coherent, linking specific activities (e.g., those with long durations or shared resources) to potential under-resourcing and inefficiencies. The analysis remains consistent with the event log evidence and provides a reasoned, defensible judgment. | F156: =RIGHT(LEFT(E156,3),1) -> 3
A157: =_xlfn.CONCAT(C157,"_",D157) -> qwen3_US37581_Q23 | B157: gpt-5-chat-latest | C157: qwen3_US37581 | D157: Q23 | E157: **3** The final answer is detailed, structured, and fully addresses the question about improving the project’s outcome. It identifies specific bottlenecks (long or overlapping tasks, resource contention, client approvals), links them explicitly to the event log data, and proposes targeted, actionable improvements (better scheduling, resource allocation, modularization, risk and client management, postimplementation planning). The reasoning is coherent and projectmanagement specific, showing insight into how the project could have been optimized. | F157: =RIGHT(LEFT(E157,3),1) -> 3
A158: =_xlfn.CONCAT(C158,"_",D158) -> qwen3_US37581_Q24 | B158: gpt-5-chat-latest | C158: qwen3_US37581 | D158: Q24 | E158: **3 –** The final answer gives a clear, evidence-based conclusion. It identifies specific long-duration tasks, relates them to milestone delays, and supports the judgment that although all activities were completed, several milestones were not achieved as planned. The reasoning is consistent with the data in the event log and appropriately cautious about missing baseline information. | F158: =RIGHT(LEFT(E158,3),1) -> 3
